[{"doi":"10.1023/b:phil.0000007402.62939.0f","title":"Author Index Volume 116 2003","authors":[],"journal":"phil-studies","published":"2003-12-01","volume":"116","issue":"3","pages":"326-326","abstract":"","topics":[],"si":null,"url":"https://doi.org/10.1023/b:phil.0000007402.62939.0f"},{"doi":"10.1023/b:phil.0000007237.51867.14","title":"Not All Worlds Are Stages","authors":["Joshua M. Stuchlik"],"journal":"phil-studies","published":"2003-12-01","volume":"116","issue":"3","pages":"309-321","abstract":"","topics":[],"si":null,"url":"https://doi.org/10.1023/b:phil.0000007237.51867.14"},{"doi":"10.1023/b:phil.0000007391.83848.bd","title":"Instructions for Authors","authors":[],"journal":"phil-studies","published":"2003-12-01","volume":"116","issue":"3","pages":"323-324","abstract":"","topics":[],"si":null,"url":"https://doi.org/10.1023/b:phil.0000007391.83848.bd"},{"doi":"10.1023/b:phil.0000007243.60727.d4","title":"Defending a Possible-Worlds Account of Indicative Conditionals","authors":["Daniel Nolan"],"journal":"phil-studies","published":"2003-12-01","volume":"116","issue":"3","pages":"215-269","abstract":"","topics":[],"si":null,"url":"https://doi.org/10.1023/b:phil.0000007243.60727.d4"},{"doi":"10.1023/b:phil.0000007204.53683.d7","title":"Is Intentionality Dependent upon Consciousness?","authors":["Uriah Kriegel"],"journal":"phil-studies","published":"2003-12-01","volume":"116","issue":"3","pages":"271-307","abstract":"","topics":["mind"],"si":null,"url":"https://doi.org/10.1023/b:phil.0000007204.53683.d7"},{"doi":"10.1023/b:phil.0000005841.01928.81","title":"Long as You Love Me, It's Alright?","authors":["Henry S. Richardson"],"journal":"phil-studies","published":"2003-11-01","volume":"116","issue":"2","pages":"183-195","abstract":"","topics":[],"si":null,"url":"https://doi.org/10.1023/b:phil.0000005841.01928.81"},{"doi":"10.1023/b:phil.0000005842.73630.a6","title":"Reply to Gaus, Richardson, and Weber","authors":["Christopher McMahon"],"journal":"phil-studies","published":"2003-11-01","volume":"116","issue":"2","pages":"197-213","abstract":"","topics":[],"si":null,"url":"https://doi.org/10.1023/b:phil.0000005842.73630.a6"},{"doi":"10.1023/b:phil.0000005838.83795.3a","title":"Collective Rationality and Collective Reasoning","authors":["Christopher McMahon"],"journal":"phil-studies","published":"2003-11-01","volume":"116","issue":"2","pages":"153-157","abstract":"","topics":["epistemology","social"],"si":null,"url":"https://doi.org/10.1023/b:phil.0000005838.83795.3a"},{"doi":"10.1023/b:phil.0000005839.21433.88","title":"Once More Unto the Breach, My Dear Friends, Once More","authors":["Gerald F. Gaus"],"journal":"phil-studies","published":"2003-11-01","volume":"116","issue":"2","pages":"159-170","abstract":"","topics":[],"si":null,"url":"https://doi.org/10.1023/b:phil.0000005839.21433.88"},{"doi":"10.1023/b:phil.0000005744.80837.65","title":"Defending Double Effect","authors":["Alison Hills"],"journal":"phil-studies","published":"2003-11-01","volume":"116","issue":"2","pages":"133-152","abstract":"","topics":[],"si":null,"url":"https://doi.org/10.1023/b:phil.0000005744.80837.65"},{"doi":"10.1023/b:phil.0000005840.06461.f0","title":"The Reason to Contribute to Cooperative Schemes","authors":["Michael Weber"],"journal":"phil-studies","published":"2003-11-01","volume":"116","issue":"2","pages":"171-181","abstract":"","topics":[],"si":null,"url":"https://doi.org/10.1023/b:phil.0000005840.06461.f0"},{"doi":"10.1023/b:phil.0000005733.01648.95","title":"Physical Constituents of Qualia","authors":["István Aranyosi"],"journal":"phil-studies","published":"2003-11-01","volume":"116","issue":"2","pages":"103-131","abstract":"","topics":["mind"],"si":null,"url":"https://doi.org/10.1023/b:phil.0000005733.01648.95"},{"doi":"10.1023/b:phil.0000005533.25543.36","title":"Empty Names and `Gappy' Propositions","authors":["Anthony Everett"],"journal":"phil-studies","published":"2003-10-01","volume":"116","issue":"1","pages":"1-36","abstract":"","topics":["language"],"si":null,"url":"https://doi.org/10.1023/b:phil.0000005533.25543.36"},{"doi":"10.1023/b:phil.0000005559.77848.5d","title":"Just Savings and the Difference Principle","authors":["Steven Wall"],"journal":"phil-studies","published":"2003-10-01","volume":"116","issue":"1","pages":"79-102","abstract":"","topics":[],"si":null,"url":"https://doi.org/10.1023/b:phil.0000005559.77848.5d"},{"doi":"10.1023/b:phil.0000005558.40211.01","title":"Williamson on Knowledge and Psychological Explanation","authors":["P.D. Magnus","Jonathan Cohen"],"journal":"phil-studies","published":"2003-10-01","volume":"116","issue":"1","pages":"37-52","abstract":"","topics":["epistemology","philsci"],"si":null,"url":"https://doi.org/10.1023/b:phil.0000005558.40211.01"},{"doi":"10.1023/b:phil.0000005563.62257.54","title":"Anti-Individualism, Conceptual Omniscience, and Skepticism","authors":["Sanford C. Goldberg"],"journal":"phil-studies","published":"2003-10-01","volume":"116","issue":"1","pages":"53-78","abstract":"","topics":["epistemology"],"si":null,"url":"https://doi.org/10.1023/b:phil.0000005563.62257.54"},{"doi":"10.1023/a:1025124607332","title":"What’s so Transparent about Transparency?","authors":["Amy Kind"],"journal":"phil-studies","published":"2003-09-01","volume":"115","issue":"3","pages":"225-244","abstract":"","topics":[],"si":null,"url":"https://doi.org/10.1023/a:1025124607332"},{"doi":"10.1023/a:1025146022431","title":"Compatibilism: The Argument From Shallowness","authors":["Saul Smilansky"],"journal":"phil-studies","published":"2003-09-01","volume":"115","issue":"3","pages":"257-282","abstract":"","topics":[],"si":null,"url":"https://doi.org/10.1023/a:1025146022431"},{"doi":"10.1023/a:1025165124028","title":"Author index 115 2003","authors":[],"journal":"phil-studies","published":"2003-09-01","volume":"115","issue":"3","pages":"308-308","abstract":"","topics":[],"si":null,"url":"https://doi.org/10.1023/a:1025165124028"},{"doi":"10.1023/a:1025157101089","title":"Does Belief Have an Aim?","authors":["David John Owens"],"journal":"phil-studies","published":"2003-09-01","volume":"115","issue":"3","pages":"283-305","abstract":"","topics":["epistemology"],"si":null,"url":"https://doi.org/10.1023/a:1025157101089"},{"doi":"10.1023/a:1025100125602","title":"“Paging Dr. Lauben! Dr. Gustav Lauben!”: Some Questions about Individualism and Competence","authors":["Arthur Sullivan"],"journal":"phil-studies","published":"2003-09-01","volume":"115","issue":"3","pages":"201-224","abstract":"","topics":[],"si":null,"url":"https://doi.org/10.1023/a:1025100125602"},{"doi":"10.1023/a:1025129319705","title":"Tye’s Representationalism: Feeling the Heat?","authors":["Richard Gray"],"journal":"phil-studies","published":"2003-09-01","volume":"115","issue":"3","pages":"245-256","abstract":"","topics":["mind"],"si":null,"url":"https://doi.org/10.1023/a:1025129319705"},{"doi":"10.1023/a:1025050806424","title":"Actualism and Higher-Order Worlds","authors":["Reina Hayaki"],"journal":"phil-studies","published":"2003-08-01","volume":"115","issue":"2","pages":"149-178","abstract":"","topics":[],"si":null,"url":"https://doi.org/10.1023/a:1025050806424"},{"doi":"10.1023/a:1025098005593","title":"Russellianism and Referential Uses of Descriptions","authors":["Neil Feit"],"journal":"phil-studies","published":"2003-08-01","volume":"115","issue":"2","pages":"99-122","abstract":"","topics":[],"si":null,"url":"https://doi.org/10.1023/a:1025098005593"},{"doi":"10.1023/a:1025093302392","title":"Much Ado About Nothing: Critical Realism Examined","authors":["R. Hanley"],"journal":"phil-studies","published":"2003-08-01","volume":"115","issue":"2","pages":"123-147","abstract":"","topics":["metaphysics"],"si":null,"url":"https://doi.org/10.1023/a:1025093302392"},{"doi":"10.1023/a:1025030803776","title":"An Objection to Attitudinal Hedonism","authors":["Peter de Marneffe"],"journal":"phil-studies","published":"2003-08-01","volume":"115","issue":"2","pages":"197-200","abstract":"","topics":[],"si":null,"url":"https://doi.org/10.1023/a:1025030803776"},{"doi":"10.1023/a:1025094823262","title":"Willing Belief and the Norm of Truth","authors":["Eric Funkhouser"],"journal":"phil-studies","published":"2003-08-01","volume":"115","issue":"2","pages":"179-195","abstract":"","topics":["epistemology"],"si":null,"url":"https://doi.org/10.1023/a:1025094823262"},{"doi":"10.1023/a:1024981602742","title":"Knowing Facts and Believing Propositions: A Solution to the Problem of Doxastic Shift","authors":["Marc A. Moffett"],"journal":"phil-studies","published":"2003-07-01","volume":"115","issue":"1","pages":"81-97","abstract":"","topics":["language"],"si":null,"url":"https://doi.org/10.1023/a:1024981602742"},{"doi":"10.1023/a:1024908230635","title":"Tarski and the Metalinguistic Liar","authors":["Greg Ray"],"journal":"phil-studies","published":"2003-07-01","volume":"115","issue":"1","pages":"55-80","abstract":"","topics":["language"],"si":null,"url":"https://doi.org/10.1023/a:1024908230635"},{"doi":"10.1023/a:1024961917413","title":"What Good are Counterexamples?","authors":["Brian Weatherson"],"journal":"phil-studies","published":"2003-07-01","volume":"115","issue":"1","pages":"1-31","abstract":"","topics":[],"si":null,"url":"https://doi.org/10.1023/a:1024961917413"},{"doi":"10.1023/a:1024919818322","title":"When Pains are Mental Objects","authors":["Abraham Olivier"],"journal":"phil-studies","published":"2003-07-01","volume":"115","issue":"1","pages":"33-53","abstract":"","topics":["mind"],"si":null,"url":"https://doi.org/10.1023/a:1024919818322"},{"doi":"10.1023/a:1024996503555","title":"Author Index, Volume 114, 2003","authors":[],"journal":"phil-studies","published":"2003-06-01","volume":"114","issue":"3","pages":"294-294","abstract":"","topics":[],"si":null,"url":"https://doi.org/10.1023/a:1024996503555"},{"doi":"10.1023/a:1024900720697","title":"No-common-cause EPR-like Funny Business in Branching Space-times","authors":["Nuel Belnap"],"journal":"phil-studies","published":"2003-06-01","volume":"114","issue":"3","pages":"199-221","abstract":"","topics":[],"si":null,"url":"https://doi.org/10.1023/a:1024900720697"},{"doi":"10.1023/a:1024940515305","title":"Evidential Atheism","authors":["Jim Stone"],"journal":"phil-studies","published":"2003-06-01","volume":"114","issue":"3","pages":"253-277","abstract":"","topics":["epistemology","religion"],"si":null,"url":"https://doi.org/10.1023/a:1024940515305"},{"doi":"10.1023/a:1024904828212","title":"Definite Descriptions without Uniqueness: A Reply to Abbott","authors":["Zoltán G. Szabó"],"journal":"phil-studies","published":"2003-06-01","volume":"114","issue":"3","pages":"279-291","abstract":"","topics":[],"si":null,"url":"https://doi.org/10.1023/a:1024904828212"},{"doi":"10.1023/a:1024967701483","title":"Modal Fictionalism and Compositionality","authors":["Josh Dever"],"journal":"phil-studies","published":"2003-06-01","volume":"114","issue":"3","pages":"223-251","abstract":"","topics":["aesthetics","metaphysics"],"si":null,"url":"https://doi.org/10.1023/a:1024967701483"},{"doi":"10.1023/a:1024417403106","title":"Non-Egalitarianism","authors":["Michael Huemer"],"journal":"phil-studies","published":"2003-05-01","volume":"114","issue":"1-2","pages":"147-171","abstract":"","topics":["political"],"si":null,"url":"https://doi.org/10.1023/a:1024417403106"},{"doi":"10.1023/a:1024469419944","title":"The Potentiality Problem","authors":["Elizabeth Harman"],"journal":"phil-studies","published":"2003-05-01","volume":"114","issue":"1-2","pages":"173-198","abstract":"","topics":[],"si":null,"url":"https://doi.org/10.1023/a:1024469419944"},{"doi":"10.1023/a:1024461218127","title":"Causation and the Making/Allowing Distinction","authors":["Sarah McGrath"],"journal":"phil-studies","published":"2003-05-01","volume":"114","issue":"1-2","pages":"81-106","abstract":"","topics":["metaphysics"],"si":null,"url":"https://doi.org/10.1023/a:1024461218127"},{"doi":"10.1023/a:1024465319036","title":"Against Vague Existence","authors":["Theodore Sider"],"journal":"phil-studies","published":"2003-05-01","volume":"114","issue":"1-2","pages":"135-146","abstract":"","topics":[],"si":null,"url":"https://doi.org/10.1023/a:1024465319036"},{"doi":"10.1023/a:1024457117218","title":"Overdetermining Causes","authors":["Jonathan Schaffer"],"journal":"phil-studies","published":"2003-05-01","volume":"114","issue":"1-2","pages":"23-45","abstract":"","topics":[],"si":null,"url":"https://doi.org/10.1023/a:1024457117218"},{"doi":"10.1023/a:1024471800380","title":"The Immorality of Modal Realism, Or: How I Learned to Stop Worrying and Let the Children Drown","authors":["Mark Heller"],"journal":"phil-studies","published":"2003-05-01","volume":"114","issue":"1-2","pages":"1-22","abstract":"","topics":["ethics","metaphysics"],"si":null,"url":"https://doi.org/10.1023/a:1024471800380"},{"doi":"10.1023/a:1024409201289","title":"Doxastic Compatibilism and the Ethics of Belief","authors":["Sharon Ryan"],"journal":"phil-studies","published":"2003-05-01","volume":"114","issue":"1-2","pages":"47-79","abstract":"","topics":["epistemology","ethics"],"si":null,"url":"https://doi.org/10.1023/a:1024409201289"},{"doi":"10.1023/a:1024413302197","title":"The Crooked Path from Vagueness to Four-Dimensionalism","authors":["Kathrin Koslicki"],"journal":"phil-studies","published":"2003-05-01","volume":"114","issue":"1-2","pages":"107-134","abstract":"","topics":[],"si":null,"url":"https://doi.org/10.1023/a:1024413302197"},{"doi":"10.1023/a:1024088203357","title":"Consciousness and Nonconceptual Content","authors":["Alex Byrne"],"journal":"phil-studies","published":"2003-04-01","volume":"113","issue":"3","pages":"261-274","abstract":"","topics":["mind"],"si":null,"url":"https://doi.org/10.1023/a:1024088203357"},{"doi":"10.1023/a:1024063903859","title":"A Reply to Szabó’s “Descriptions and Uniqueness”","authors":["Barbara Abbott"],"journal":"phil-studies","published":"2003-04-01","volume":"113","issue":"3","pages":"223-231","abstract":"","topics":[],"si":null,"url":"https://doi.org/10.1023/a:1024063903859"},{"doi":"10.1023/a:1024044421104","title":"The Panic Theory – Reply to Byrne","authors":["Michael Tye"],"journal":"phil-studies","published":"2003-04-01","volume":"113","issue":"3","pages":"287-290","abstract":"","topics":[],"si":null,"url":"https://doi.org/10.1023/a:1024044421104"},{"doi":"10.1023/a:1024040320196","title":"On the Virtue of Being Poised – Reply to Seager","authors":["Michael Tye"],"journal":"phil-studies","published":"2003-04-01","volume":"113","issue":"3","pages":"275-280","abstract":"","topics":["ethics"],"si":null,"url":"https://doi.org/10.1023/a:1024040320196"},{"doi":"10.1023/a:1024075818378","title":"Consciousness, Color, and Content","authors":["Michael Tye"],"journal":"phil-studies","published":"2003-04-01","volume":"113","issue":"3","pages":"233-235","abstract":"","topics":["mind"],"si":null,"url":"https://doi.org/10.1023/a:1024075818378"},{"doi":"10.1023/a:1024037729994","title":"The Impossibility of Superdupervenience","authors":["Micahel P. Lynch","Joshua M. Glasgow"],"journal":"phil-studies","published":"2003-04-01","volume":"113","issue":"3","pages":"201-221","abstract":"","topics":[],"si":null,"url":"https://doi.org/10.1023/a:1024037729994"},{"doi":"10.1023/a:1024084102449","title":"Tye on Consciousness: Time to Panic?","authors":["William E. Seager"],"journal":"phil-studies","published":"2003-04-01","volume":"113","issue":"3","pages":"237-247","abstract":"","topics":["metaphysics","mind"],"si":null,"url":"https://doi.org/10.1023/a:1024084102449"},{"doi":"10.1023/a:1024019914033","title":"Author Index • Volume 113 • 2003","authors":[],"journal":"phil-studies","published":"2003-04-01","volume":"113","issue":"3","pages":"292-292","abstract":"","topics":[],"si":null,"url":"https://doi.org/10.1023/a:1024019914033"},{"doi":"10.1023/a:1024036219287","title":"Tye: Consciousness, Color and Content","authors":["Barry Maud"],"journal":"phil-studies","published":"2003-04-01","volume":"113","issue":"3","pages":"249-260","abstract":"","topics":["mind"],"si":null,"url":"https://doi.org/10.1023/a:1024036219287"},{"doi":"10.1023/a:1024092304266","title":"Phenomenal Character and Color – Reply to Maund","authors":["Michael Tye"],"journal":"phil-studies","published":"2003-04-01","volume":"113","issue":"3","pages":"281-285","abstract":"","topics":["mind"],"si":null,"url":"https://doi.org/10.1023/a:1024092304266"},{"doi":"10.1023/a:1023071410620","title":"Presentism and the Non-Present","authors":["Matthew Davidson"],"journal":"phil-studies","published":"2003-03-01","volume":"113","issue":"1","pages":"77-92","abstract":"","topics":[],"si":null,"url":"https://doi.org/10.1023/a:1023071410620"},{"doi":"10.1023/a:1023028523207","title":"Are Truth and Reference Quasi-Disquotational?","authors":["Ray Buchanan"],"journal":"phil-studies","published":"2003-03-01","volume":"113","issue":"1","pages":"43-75","abstract":"","topics":["language"],"si":null,"url":"https://doi.org/10.1023/a:1023028523207"},{"doi":"10.1023/a:1023978327000","title":"Dynamic Inconsistency and Performable Plans","authors":["Erik Carlson"],"journal":"phil-studies","published":"2003-03-01","volume":"113","issue":"2","pages":"181-200","abstract":"","topics":[],"si":null,"url":"https://doi.org/10.1023/a:1023978327000"},{"doi":"10.1023/a:1023940209581","title":"Free Will, Chance, and Mystery","authors":["L. Ekstrom"],"journal":"phil-studies","published":"2003-03-01","volume":"113","issue":"2","pages":"153-180","abstract":"","topics":["metaphysics"],"si":null,"url":"https://doi.org/10.1023/a:1023940209581"},{"doi":"10.1023/a:1023931723132","title":"Lucky Libertarianism","authors":["M. Almeida","M. Bernstein"],"journal":"phil-studies","published":"2003-03-01","volume":"113","issue":"2","pages":"93-119","abstract":"","topics":["political"],"si":null,"url":"https://doi.org/10.1023/a:1023931723132"},{"doi":"10.1023/a:1023074316190","title":"Color: A Functionalist Proposal","authors":["Jonathan Cohen"],"journal":"phil-studies","published":"2003-03-01","volume":"113","issue":"1","pages":"1-42","abstract":"","topics":[],"si":null,"url":"https://doi.org/10.1023/a:1023074316190"},{"doi":"10.1023/a:1023962226419","title":"Moral Explanation and the Special Sciences","authors":["B. Majors"],"journal":"phil-studies","published":"2003-03-01","volume":"113","issue":"2","pages":"121-152","abstract":"","topics":["ethics","philsci"],"si":null,"url":"https://doi.org/10.1023/a:1023962226419"},{"doi":"10.1023/a:1023082800260","title":"Do Vague Probabilities Really Scotch Pascal’s Wager?","authors":["Craig Duncan"],"journal":"phil-studies","published":"2003-02-01","volume":"112","issue":"3","pages":"279-290","abstract":"","topics":["philsci"],"si":null,"url":"https://doi.org/10.1023/a:1023082800260"},{"doi":"10.1023/a:1023002625641","title":"What is Externalism?","authors":["Katalin Farkas"],"journal":"phil-studies","published":"2003-02-01","volume":"112","issue":"3","pages":"187-208","abstract":"","topics":["epistemology"],"si":null,"url":"https://doi.org/10.1023/a:1023002625641"},{"doi":"10.1023/a:1023075527458","title":"Of Brains in Vats, Whatever Brains in Vats May Be","authors":["Bredo C. Johnsen"],"journal":"phil-studies","published":"2003-02-01","volume":"112","issue":"3","pages":"225-249","abstract":"","topics":[],"si":null,"url":"https://doi.org/10.1023/a:1023075527458"},{"doi":"10.1023/a:1023004203043","title":"Presupposition and Accommodation: Understanding the Stalnakerian Picture","authors":["Mandy Simons"],"journal":"phil-studies","published":"2003-02-01","volume":"112","issue":"3","pages":"251-278","abstract":"","topics":["epistemology"],"si":null,"url":"https://doi.org/10.1023/a:1023004203043"},{"doi":"10.1023/a:1023019409711","title":"A Metacompatibilist Account of Free Will: Making Compatibilists and Incompatibilists More Compatible","authors":["Bruce N. Waller"],"journal":"phil-studies","published":"2003-02-01","volume":"112","issue":"3","pages":"209-224","abstract":"","topics":["metaphysics"],"si":null,"url":"https://doi.org/10.1023/a:1023019409711"},{"doi":"10.1023/a:1022594905241","title":"Why the handicapped child case is hard","authors":["Josh Parsons"],"journal":"phil-studies","published":"2003-01-01","volume":"112","issue":"2","pages":"147-162","abstract":"","topics":[],"si":null,"url":"https://doi.org/10.1023/a:1022594905241"},{"doi":"10.1023/a:1022558420553","title":"A Defense of Two Optimistic Claims in Ethical Theory","authors":["Stuart Rachels"],"journal":"phil-studies","published":"2003-01-01","volume":"112","issue":"1","pages":"1-30","abstract":"","topics":["ethics"],"si":null,"url":"https://doi.org/10.1023/a:1022558420553"},{"doi":"10.1023/a:1022555113538","title":"The Lowe Road to the Problem of Temporary Intrinsics","authors":["Lawrence B. Lombard"],"journal":"phil-studies","published":"2003-01-01","volume":"112","issue":"2","pages":"163-185","abstract":"","topics":[],"si":null,"url":"https://doi.org/10.1023/a:1022555113538"},{"doi":"10.1023/a:1022538609397","title":"A Critique of Langsam's “The Theory of Appearing Defended”","authors":["George Djukic","Vladimir B. Popescu"],"journal":"phil-studies","published":"2003-01-01","volume":"112","issue":"1","pages":"69-91","abstract":"","topics":[],"si":null,"url":"https://doi.org/10.1023/a:1022538609397"},{"doi":"10.1023/a:1022579621057","title":"The Metaphysics of Velocity","authors":["Ulrich Meyer"],"journal":"phil-studies","published":"2003-01-01","volume":"112","issue":"1","pages":"93-102","abstract":"","topics":["metaphysics","philsci"],"si":null,"url":"https://doi.org/10.1023/a:1022579621057"},{"doi":"10.1023/a:1022542004219","title":"Reasons Explanations and Pure Agency","authors":["Richard Feldman","Andrei A. Buckareff"],"journal":"phil-studies","published":"2003-01-01","volume":"112","issue":"2","pages":"135-145","abstract":"","topics":["action","philsci"],"si":null,"url":"https://doi.org/10.1023/a:1022542004219"},{"doi":"10.1023/a:1022555718825","title":"Counterfactuals for Consequentialists","authors":["Jean-Paul Vessel"],"journal":"phil-studies","published":"2003-01-01","volume":"112","issue":"2","pages":"103-125","abstract":"","topics":["ethics"],"si":null,"url":"https://doi.org/10.1023/a:1022555718825"},{"doi":"10.1023/a:1022582325326","title":"The Moral Relevance of Cost","authors":["Bashshar Haydar"],"journal":"phil-studies","published":"2003-01-01","volume":"112","issue":"2","pages":"127-134","abstract":"","topics":["ethics"],"si":null,"url":"https://doi.org/10.1023/a:1022582325326"},{"doi":"10.1023/a:1022590626235","title":"Perceptual Knowledge Derailed","authors":["J. Schaffer"],"journal":"phil-studies","published":"2003-01-01","volume":"112","issue":"1","pages":"31-45","abstract":"","topics":["epistemology","mind"],"si":null,"url":"https://doi.org/10.1023/a:1022590626235"},{"doi":"10.1023/a:1022542710305","title":"Deflationism and the Normativity of Truth","authors":["Matthew McGrath"],"journal":"phil-studies","published":"2003-01-01","volume":"112","issue":"1","pages":"47-67","abstract":"","topics":["ethics"],"si":null,"url":"https://doi.org/10.1023/a:1022542710305"}]