[{"doi":"10.1007/s11098-010-9689-7","title":"Silins’s Liberalism","authors":["Matthew Kotzen"],"journal":"phil-studies","published":"2010-12-30","volume":"159","issue":"1","pages":"61-68","abstract":"","topics":["political"],"si":null,"url":"https://doi.org/10.1007/s11098-010-9689-7"},{"doi":"10.1007/s11098-010-9686-x","title":"Resolving arguments by different conceptual traditions of realization","authors":["Ronald Endicott"],"journal":"phil-studies","published":"2010-12-24","volume":"159","issue":"1","pages":"41-59","abstract":"","topics":[],"si":null,"url":"https://doi.org/10.1007/s11098-010-9686-x"},{"doi":"10.1007/s11098-010-9684-z","title":"Frictional coherentism? A comment on chapter 10 of Ernest Sosa’s Reflective Knowledge","authors":["Crispin Wright"],"journal":"phil-studies","published":"2010-12-24","volume":"153","issue":"1","pages":"29-41","abstract":"","topics":["epistemology"],"si":"reflective knowledge (OUP, 2009)","url":"https://doi.org/10.1007/s11098-010-9684-z"},{"doi":"10.1007/s11098-010-9678-x","title":"Imaginative resistance without conflict","authors":["Anna Mahtani"],"journal":"phil-studies","published":"2010-12-19","volume":"158","issue":"3","pages":"415-429","abstract":"","topics":[],"si":null,"url":"https://doi.org/10.1007/s11098-010-9678-x"},{"doi":"10.1007/s11098-010-9674-1","title":"Manifesting belief in absolute necessity","authors":["John Divers","Daniel Y. Elstein"],"journal":"phil-studies","published":"2010-12-17","volume":"158","issue":"1","pages":"109-130","abstract":"","topics":["epistemology"],"si":null,"url":"https://doi.org/10.1007/s11098-010-9674-1"},{"doi":"10.1007/s11098-010-9677-y","title":"Propositions, semantic values, and rigidity","authors":["Dilip Ninan"],"journal":"phil-studies","published":"2010-12-17","volume":"158","issue":"3","pages":"401-413","abstract":"","topics":["language"],"si":null,"url":"https://doi.org/10.1007/s11098-010-9677-y"},{"doi":"10.1007/s11098-010-9676-z","title":"Arbitrary reference","authors":["Wylie Breckenridge","Ofra Magidor"],"journal":"phil-studies","published":"2010-12-15","volume":"158","issue":"3","pages":"377-400","abstract":"","topics":["language"],"si":null,"url":"https://doi.org/10.1007/s11098-010-9676-z"},{"doi":"10.1007/s11098-010-9675-0","title":"Implicit definition and the application of logic","authors":["Thomas Kroedel"],"journal":"phil-studies","published":"2010-12-15","volume":"158","issue":"1","pages":"131-148","abstract":"","topics":["logic"],"si":null,"url":"https://doi.org/10.1007/s11098-010-9675-0"},{"doi":"10.1007/s11098-010-9647-4","title":"Sosa on easy knowledge and the problem of the criterion","authors":["James Van Cleve"],"journal":"phil-studies","published":"2010-12-14","volume":"153","issue":"1","pages":"19-28","abstract":"","topics":["epistemology"],"si":"reflective knowledge (OUP, 2009)","url":"https://doi.org/10.1007/s11098-010-9647-4"},{"doi":"10.1007/s11098-010-9679-9","title":"McTaggart and indexing the copula","authors":["Bradley Rettler"],"journal":"phil-studies","published":"2010-12-11","volume":"158","issue":"3","pages":"431-434","abstract":"","topics":[],"si":null,"url":"https://doi.org/10.1007/s11098-010-9679-9"},{"doi":"10.1007/s11098-010-9680-3","title":"Evidential externalism","authors":["Jeffrey Dunn"],"journal":"phil-studies","published":"2010-12-10","volume":"158","issue":"3","pages":"435-455","abstract":"","topics":["epistemology"],"si":null,"url":"https://doi.org/10.1007/s11098-010-9680-3"},{"doi":"10.1007/s11098-010-9683-0","title":"Causes of causes","authors":["Alex Broadbent"],"journal":"phil-studies","published":"2010-12-10","volume":"158","issue":"3","pages":"457-476","abstract":"","topics":[],"si":null,"url":"https://doi.org/10.1007/s11098-010-9683-0"},{"doi":"10.1007/s11098-010-9681-2","title":"Modal Mereology and Modal Supervenience","authors":["Sean Drysdale Walsh"],"journal":"phil-studies","published":"2010-12-09","volume":"159","issue":"1","pages":"1-20","abstract":"","topics":["metaphysics"],"si":null,"url":"https://doi.org/10.1007/s11098-010-9681-2"},{"doi":"10.1007/s11098-010-9669-y","title":"Replies to critics","authors":["John Martin Fischer"],"journal":"phil-studies","published":"2010-12-05","volume":"158","issue":"3","pages":"529-540","abstract":"","topics":[],"si":null,"url":"https://doi.org/10.1007/s11098-010-9669-y"},{"doi":"10.1007/s11098-010-9672-3","title":"Logical knowledge and ordinary reasoning","authors":["Corine Besson"],"journal":"phil-studies","published":"2010-12-03","volume":"158","issue":"1","pages":"59-82","abstract":"","topics":["epistemology","logic"],"si":null,"url":"https://doi.org/10.1007/s11098-010-9672-3"},{"doi":"10.1007/s11098-010-9666-1","title":"Rigidification and attitudes","authors":["Bryan Pickel"],"journal":"phil-studies","published":"2010-12-01","volume":"158","issue":"1","pages":"43-58","abstract":"","topics":[],"si":null,"url":"https://doi.org/10.1007/s11098-010-9666-1"},{"doi":"10.1007/s11098-010-9661-6","title":"Evolved cognitive biases and the epistemic status of scientific beliefs","authors":["Helen De Cruz","Johan De Smedt"],"journal":"phil-studies","published":"2010-11-28","volume":"157","issue":"3","pages":"411-429","abstract":"","topics":["epistemology","mind","philsci"],"si":null,"url":"https://doi.org/10.1007/s11098-010-9661-6"},{"doi":"10.1007/s11098-010-9667-0","title":"Fischer on death and unexperienced evils","authors":["Ben Bradley"],"journal":"phil-studies","published":"2010-11-27","volume":"158","issue":"3","pages":"507-513","abstract":"","topics":[],"si":null,"url":"https://doi.org/10.1007/s11098-010-9667-0"},{"doi":"10.1007/s11098-010-9627-8","title":"Reply to Lasersohn, MacFarlane, and Richard","authors":["Herman Cappelen","John Hawthorne"],"journal":"phil-studies","published":"2010-11-26","volume":"156","issue":"3","pages":"449-466","abstract":"","topics":[],"si":null,"url":"https://doi.org/10.1007/s11098-010-9627-8"},{"doi":"10.1007/s11098-010-9668-z","title":"Precis, our stories: essays on life, death, and free will","authors":["John Martin Fischer"],"journal":"phil-studies","published":"2010-11-23","volume":"158","issue":"3","pages":"503-506","abstract":"","topics":["metaphysics"],"si":null,"url":"https://doi.org/10.1007/s11098-010-9668-z"},{"doi":"10.1007/s11098-010-9638-5","title":"Further thoughts on memory: replies to Schechtman, Adams, and Goldberg","authors":["Sven Bernecker"],"journal":"phil-studies","published":"2010-11-21","volume":"153","issue":"1","pages":"109-121","abstract":"","topics":["mind"],"si":"reflective knowledge (OUP, 2009)","url":"https://doi.org/10.1007/s11098-010-9638-5"},{"doi":"10.1007/s11098-010-9671-4","title":"Comments on John Martin Fischer’s Our Stories","authors":["J. David Velleman"],"journal":"phil-studies","published":"2010-11-21","volume":"158","issue":"3","pages":"515-521","abstract":"","topics":[],"si":null,"url":"https://doi.org/10.1007/s11098-010-9671-4"},{"doi":"10.1007/s11098-010-9629-6","title":"Reply to Lasersohn, MacFarlane, and Richard","authors":["Herman Cappelen","John Hawthorne"],"journal":"phil-studies","published":"2010-11-20","volume":"156","issue":"3","pages":"417-419","abstract":"","topics":[],"si":null,"url":"https://doi.org/10.1007/s11098-010-9629-6"},{"doi":"10.1007/s11098-010-9670-5","title":"On Fischer’s Our Stories","authors":["Derk Pereboom"],"journal":"phil-studies","published":"2010-11-20","volume":"158","issue":"3","pages":"523-528","abstract":"","topics":[],"si":null,"url":"https://doi.org/10.1007/s11098-010-9670-5"},{"doi":"10.1007/s11098-010-9654-5","title":"Agent causation as the solution to all the compatibilist’s problems","authors":["Ned Markosian"],"journal":"phil-studies","published":"2010-11-18","volume":"157","issue":"3","pages":"383-398","abstract":"","topics":["metaphysics"],"si":null,"url":"https://doi.org/10.1007/s11098-010-9654-5"},{"doi":"10.1007/s11098-010-9663-4","title":"Husker du?","authors":["Fred Adams"],"journal":"phil-studies","published":"2010-11-16","volume":"153","issue":"1","pages":"81-94","abstract":"","topics":[],"si":"reflective knowledge (OUP, 2009)","url":"https://doi.org/10.1007/s11098-010-9663-4"},{"doi":"10.1007/s11098-010-9665-2","title":"No bare particulars","authors":["Andrew M. Bailey"],"journal":"phil-studies","published":"2010-11-13","volume":"158","issue":"1","pages":"31-41","abstract":"","topics":[],"si":null,"url":"https://doi.org/10.1007/s11098-010-9665-2"},{"doi":"10.1007/s11098-010-9664-3","title":"Three-and-a-half folk concepts of intentional action","authors":["Alessandro Lanteri"],"journal":"phil-studies","published":"2010-11-12","volume":"158","issue":"1","pages":"17-30","abstract":"","topics":["action"],"si":null,"url":"https://doi.org/10.1007/s11098-010-9664-3"},{"doi":"10.1007/s11098-010-9648-3","title":"God’s silence","authors":["Elisa Paganini"],"journal":"phil-studies","published":"2010-11-12","volume":"157","issue":"2","pages":"287-298","abstract":"","topics":["religion"],"si":null,"url":"https://doi.org/10.1007/s11098-010-9648-3"},{"doi":"10.1007/s11098-010-9653-6","title":"Resemblance theories of properties","authors":["Alexander Paseau"],"journal":"phil-studies","published":"2010-11-11","volume":"157","issue":"3","pages":"361-382","abstract":"","topics":[],"si":null,"url":"https://doi.org/10.1007/s11098-010-9653-6"},{"doi":"10.1007/s11098-010-9637-6","title":"Smelling lessons","authors":["Clare Batty"],"journal":"phil-studies","published":"2010-11-10","volume":"153","issue":"1","pages":"161-174","abstract":"","topics":[],"si":"reflective knowledge (OUP, 2009)","url":"https://doi.org/10.1007/s11098-010-9637-6"},{"doi":"10.1007/s11098-010-9644-7","title":"Reflections on reflective knowledge","authors":["Ram Neta"],"journal":"phil-studies","published":"2010-11-04","volume":"153","issue":"1","pages":"3-17","abstract":"","topics":["epistemology"],"si":"reflective knowledge (OUP, 2009)","url":"https://doi.org/10.1007/s11098-010-9644-7"},{"doi":"10.1007/s11098-010-9642-9","title":"The metasemantics of memory","authors":["Sanford C. Goldberg"],"journal":"phil-studies","published":"2010-11-03","volume":"153","issue":"1","pages":"95-107","abstract":"","topics":["language","mind"],"si":"reflective knowledge (OUP, 2009)","url":"https://doi.org/10.1007/s11098-010-9642-9"},{"doi":"10.1007/s11098-010-9662-5","title":"Action, responsibility and the ability to do otherwise","authors":["Justin A. Capes"],"journal":"phil-studies","published":"2010-11-03","volume":"158","issue":"1","pages":"1-15","abstract":"","topics":["action","ethics"],"si":null,"url":"https://doi.org/10.1007/s11098-010-9662-5"},{"doi":"10.1007/s11098-010-9655-4","title":"Three problems for Schroeder’s hypotheticalism","authors":["Russ Shafer-Landau"],"journal":"phil-studies","published":"2010-11-03","volume":"157","issue":"3","pages":"435-443","abstract":"","topics":[],"si":null,"url":"https://doi.org/10.1007/s11098-010-9655-4"},{"doi":"10.1007/s11098-010-9660-7","title":"Rigidity and actuality-dependence","authors":["Jussi Haukioja"],"journal":"phil-studies","published":"2010-11-03","volume":"157","issue":"3","pages":"399-410","abstract":"","topics":[],"si":null,"url":"https://doi.org/10.1007/s11098-010-9660-7"},{"doi":"10.1007/s11098-010-9640-y","title":"Vicissitudes of non-visual objects: Comments on Macpherson, O’Callaghan, and Batty","authors":["Austen Clark"],"journal":"phil-studies","published":"2010-11-03","volume":"153","issue":"1","pages":"175-181","abstract":"","topics":[],"si":"reflective knowledge (OUP, 2009)","url":"https://doi.org/10.1007/s11098-010-9640-y"},{"doi":"10.1007/s11098-010-9639-4","title":"Précis of memory: a philosophical study","authors":["Sven Bernecker"],"journal":"phil-studies","published":"2010-11-02","volume":"153","issue":"1","pages":"61-64","abstract":"","topics":["mind"],"si":"reflective knowledge (OUP, 2009)","url":"https://doi.org/10.1007/s11098-010-9639-4"},{"doi":"10.1007/s11098-010-9650-9","title":"Movin’ on up: higher-level requirements and inferential justification","authors":["Chris Tucker"],"journal":"phil-studies","published":"2010-11-02","volume":"157","issue":"3","pages":"323-340","abstract":"","topics":["epistemology"],"si":null,"url":"https://doi.org/10.1007/s11098-010-9650-9"},{"doi":"10.1007/s11098-010-9656-3","title":"Response to Mark Schroeder’s Slaves of the passions","authors":["Jonathan Dancy"],"journal":"phil-studies","published":"2010-11-02","volume":"157","issue":"3","pages":"455-462","abstract":"","topics":[],"si":null,"url":"https://doi.org/10.1007/s11098-010-9656-3"},{"doi":"10.1007/s11098-010-9646-5","title":"Replies to Ram Neta, James Van Cleve, and Crispin Wright for a book symposium on reflective knowledge (OUP, 2009)","authors":["Ernest Sosa"],"journal":"phil-studies","published":"2010-11-02","volume":"153","issue":"1","pages":"43-59","abstract":"","topics":["epistemology"],"si":"reflective knowledge (OUP, 2009)","url":"https://doi.org/10.1007/s11098-010-9646-5"},{"doi":"10.1007/s11098-010-9657-2","title":"Mark Schroeder’s Hypotheticalism: agent-neutrality, moral epistemology, and methodology","authors":["Tristram McPherson"],"journal":"phil-studies","published":"2010-11-02","volume":"157","issue":"3","pages":"445-453","abstract":"","topics":["epistemology","ethics"],"si":null,"url":"https://doi.org/10.1007/s11098-010-9657-2"},{"doi":"10.1007/s11098-010-9659-0","title":"Reply to Shafer-Landau, Mcpherson, and Dancy","authors":["Mark Schroeder"],"journal":"phil-studies","published":"2010-10-30","volume":"157","issue":"3","pages":"463-474","abstract":"","topics":[],"si":null,"url":"https://doi.org/10.1007/s11098-010-9659-0"},{"doi":"10.1007/s11098-010-9652-7","title":"Lessons from beyond vision (sounds and audition)","authors":["Casey O’Callaghan"],"journal":"phil-studies","published":"2010-10-30","volume":"153","issue":"1","pages":"143-160","abstract":"","topics":[],"si":"reflective knowledge (OUP, 2009)","url":"https://doi.org/10.1007/s11098-010-9652-7"},{"doi":"10.1007/s11098-010-9643-8","title":"Taxonomising the senses","authors":["Fiona Macpherson"],"journal":"phil-studies","published":"2010-10-30","volume":"153","issue":"1","pages":"123-142","abstract":"","topics":[],"si":"reflective knowledge (OUP, 2009)","url":"https://doi.org/10.1007/s11098-010-9643-8"},{"doi":"10.1007/s11098-010-9658-1","title":"Précis of Slaves of the Passions","authors":["Mark Schroeder"],"journal":"phil-studies","published":"2010-10-28","volume":"157","issue":"3","pages":"431-434","abstract":"","topics":[],"si":null,"url":"https://doi.org/10.1007/s11098-010-9658-1"},{"doi":"10.1007/s11098-010-9645-6","title":"Memory and identity","authors":["Marya Schechtman"],"journal":"phil-studies","published":"2010-10-28","volume":"153","issue":"1","pages":"65-79","abstract":"","topics":["mind"],"si":"reflective knowledge (OUP, 2009)","url":"https://doi.org/10.1007/s11098-010-9645-6"},{"doi":"10.1007/s11098-010-9651-8","title":"What in the world is weakness of will?","authors":["Joshua May","Richard Holton"],"journal":"phil-studies","published":"2010-10-28","volume":"157","issue":"3","pages":"341-360","abstract":"","topics":["action"],"si":null,"url":"https://doi.org/10.1007/s11098-010-9651-8"},{"doi":"10.1007/s11098-010-9641-x","title":"Editorial","authors":["Rebecca Copenhaver"],"journal":"phil-studies","published":"2010-10-26","volume":"153","issue":"1","pages":"1-2","abstract":"","topics":[],"si":"reflective knowledge (OUP, 2009)","url":"https://doi.org/10.1007/s11098-010-9641-x"},{"doi":"10.1007/s11098-010-9649-2","title":"Is even thought compositional?","authors":["Lenny Clapp"],"journal":"phil-studies","published":"2010-10-26","volume":"157","issue":"2","pages":"299-322","abstract":"","topics":["metaphysics"],"si":null,"url":"https://doi.org/10.1007/s11098-010-9649-2"},{"doi":"10.1007/s11098-010-9633-x","title":"Propositional structure and truth conditions","authors":["Michael McGlone"],"journal":"phil-studies","published":"2010-10-24","volume":"157","issue":"2","pages":"211-225","abstract":"","topics":["language"],"si":null,"url":"https://doi.org/10.1007/s11098-010-9633-x"},{"doi":"10.1007/s11098-010-9636-7","title":"Intrinsic value and the supervenience principle","authors":["Dale Dorsey"],"journal":"phil-studies","published":"2010-10-20","volume":"157","issue":"2","pages":"267-285","abstract":"","topics":[],"si":null,"url":"https://doi.org/10.1007/s11098-010-9636-7"},{"doi":"10.1007/s11098-010-9623-z","title":"The non-transitivity of the contingent and occasional identity relations","authors":["Ralf M. Bader"],"journal":"phil-studies","published":"2010-10-16","volume":"157","issue":"1","pages":"141-152","abstract":"","topics":[],"si":null,"url":"https://doi.org/10.1007/s11098-010-9623-z"},{"doi":"10.1007/s11098-010-9635-8","title":"Mentalist evidentialism vindicated (and a super-blooper epistemic design problem for proper function justification)","authors":["Todd R. Long"],"journal":"phil-studies","published":"2010-10-15","volume":"157","issue":"2","pages":"251-266","abstract":"","topics":["epistemology","mind"],"si":null,"url":"https://doi.org/10.1007/s11098-010-9635-8"},{"doi":"10.1007/s11098-010-9634-9","title":"Representationalism and the perspectival character of perceptual experience","authors":["René Jagnow"],"journal":"phil-studies","published":"2010-09-29","volume":"157","issue":"2","pages":"227-249","abstract":"","topics":["mind"],"si":null,"url":"https://doi.org/10.1007/s11098-010-9634-9"},{"doi":"10.1007/s11098-010-9631-z","title":"Modified Frankfurt-type counterexamples and flickers of freedom","authors":["Michael Robinson"],"journal":"phil-studies","published":"2010-09-28","volume":"157","issue":"2","pages":"177-194","abstract":"","topics":[],"si":null,"url":"https://doi.org/10.1007/s11098-010-9631-z"},{"doi":"10.1007/s11098-010-9597-x","title":"Précis of Supersizing the mind: embodiment, action, and cognitive extension (Oxford University Press, NY, 2008)","authors":["Andy Clark"],"journal":"phil-studies","published":"2010-09-28","volume":"152","issue":"3","pages":"413-416","abstract":"","topics":["action","mind"],"si":"Supersizing the Mind: Embodiment, Action, and Cognitive Extension (Oxford University Press, NY, 2008)","url":"https://doi.org/10.1007/s11098-010-9597-x"},{"doi":"10.1007/s11098-010-9630-0","title":"Internalization and moral demands","authors":["William Sin"],"journal":"phil-studies","published":"2010-09-23","volume":"157","issue":"2","pages":"163-175","abstract":"","topics":["ethics"],"si":null,"url":"https://doi.org/10.1007/s11098-010-9630-0"},{"doi":"10.1007/s11098-010-9632-y","title":"Rule-following, ideal conditions and finkish dispositions","authors":["Andrea Guardo"],"journal":"phil-studies","published":"2010-09-23","volume":"157","issue":"2","pages":"195-209","abstract":"","topics":["metaphysics"],"si":null,"url":"https://doi.org/10.1007/s11098-010-9632-y"},{"doi":"10.1007/s11098-010-9620-2","title":"Reliabilism and the extra value of knowledge","authors":["Wayne A. Davis","Christoph Jäger"],"journal":"phil-studies","published":"2010-09-23","volume":"157","issue":"1","pages":"93-105","abstract":"","topics":["epistemology"],"si":null,"url":"https://doi.org/10.1007/s11098-010-9620-2"},{"doi":"10.1007/s11098-010-9624-y","title":"A defense of contingent logical truths","authors":["Michael Nelson","Edward N. Zalta"],"journal":"phil-studies","published":"2010-09-22","volume":"157","issue":"1","pages":"153-162","abstract":"","topics":["logic"],"si":null,"url":"https://doi.org/10.1007/s11098-010-9624-y"},{"doi":"10.1007/s11098-010-9626-9","title":"Simplicity made difficult","authors":["John MacFarlane"],"journal":"phil-studies","published":"2010-09-22","volume":"156","issue":"3","pages":"441-448","abstract":"","topics":[],"si":null,"url":"https://doi.org/10.1007/s11098-010-9626-9"},{"doi":"10.1007/s11098-010-9625-x","title":"Context, relevant parts and (lack of) disagreement over taste","authors":["Peter Lasersohn"],"journal":"phil-studies","published":"2010-09-22","volume":"156","issue":"3","pages":"433-439","abstract":"","topics":["epistemology"],"si":null,"url":"https://doi.org/10.1007/s11098-010-9625-x"},{"doi":"10.1007/s11098-010-9618-9","title":"Why property dualists must reject substance physicalism","authors":["Susan Schneider"],"journal":"phil-studies","published":"2010-09-17","volume":"157","issue":"1","pages":"61-76","abstract":"","topics":[],"si":null,"url":"https://doi.org/10.1007/s11098-010-9618-9"},{"doi":"10.1007/s11098-010-9622-0","title":"Instrumental rationality, symmetry and scope","authors":["John Brunero"],"journal":"phil-studies","published":"2010-09-16","volume":"157","issue":"1","pages":"125-140","abstract":"","topics":["epistemology","mind"],"si":null,"url":"https://doi.org/10.1007/s11098-010-9622-0"},{"doi":"10.1007/s11098-010-9609-x","title":"Predicate abstraction, the limits of quantification, and the modality of existence","authors":["Philip Percival"],"journal":"phil-studies","published":"2010-09-15","volume":"156","issue":"3","pages":"389-416","abstract":"","topics":["language","logic","metaphysics"],"si":null,"url":"https://doi.org/10.1007/s11098-010-9609-x"},{"doi":"10.1007/s11098-010-9611-3","title":"The transparency of mental content revisited","authors":["Paul Boghossian"],"journal":"phil-studies","published":"2010-09-15","volume":"155","issue":"3","pages":"457-465","abstract":"","topics":["mind"],"si":null,"url":"https://doi.org/10.1007/s11098-010-9611-3"},{"doi":"10.1007/s11098-010-9619-8","title":"Resisting buck-passing accounts of prudential value","authors":["Guy Fletcher"],"journal":"phil-studies","published":"2010-09-11","volume":"157","issue":"1","pages":"77-91","abstract":"","topics":[],"si":null,"url":"https://doi.org/10.1007/s11098-010-9619-8"},{"doi":"10.1007/s11098-010-9621-1","title":"Indexical contextualism and the challenges from disagreement","authors":["Carl Baker"],"journal":"phil-studies","published":"2010-09-11","volume":"157","issue":"1","pages":"107-123","abstract":"","topics":["epistemology","language"],"si":null,"url":"https://doi.org/10.1007/s11098-010-9621-1"},{"doi":"10.1007/s11098-010-9598-9","title":"Finding the Mind: Book Symposium on Supersizing the Mind: Embodiment, Action, and Cognitive Extension (Oxford University Press, NY, 2008)","authors":["Andy Clark"],"journal":"phil-studies","published":"2010-09-07","volume":"152","issue":"3","pages":"447-461","abstract":"","topics":["action","mind"],"si":"Supersizing the Mind: Embodiment, Action, and Cognitive Extension (Oxford University Press, NY, 2008)","url":"https://doi.org/10.1007/s11098-010-9598-9"},{"doi":"10.1007/s11098-010-9613-1","title":"Stalnaker on sleeping beauty","authors":["Brian Weatherson"],"journal":"phil-studies","published":"2010-09-03","volume":"155","issue":"3","pages":"445-456","abstract":"","topics":["aesthetics"],"si":null,"url":"https://doi.org/10.1007/s11098-010-9613-1"},{"doi":"10.1007/s11098-010-9612-2","title":"On the self-locating response to the knowledge argument","authors":["Daniel Stoljar"],"journal":"phil-studies","published":"2010-09-03","volume":"155","issue":"3","pages":"437-443","abstract":"","topics":["epistemology"],"si":null,"url":"https://doi.org/10.1007/s11098-010-9612-2"},{"doi":"10.1007/s11098-010-9604-2","title":"Phenomenal intentionality and the evidential role of perceptual experience: comments on Jack Lyons, Perception and Basic Beliefs","authors":["Terry Horgan"],"journal":"phil-studies","published":"2010-09-02","volume":"153","issue":"3","pages":"447-455","abstract":"","topics":["epistemology","mind"],"si":null,"url":"https://doi.org/10.1007/s11098-010-9604-2"},{"doi":"10.1007/s11098-010-9617-x","title":"Taking aim at the truth","authors":["Masahiro Yamada"],"journal":"phil-studies","published":"2010-09-02","volume":"157","issue":"1","pages":"47-59","abstract":"","topics":[],"si":null,"url":"https://doi.org/10.1007/s11098-010-9617-x"},{"doi":"10.1007/s11098-010-9616-y","title":"The phenomenological character of color perception","authors":["Edward Wilson Averill"],"journal":"phil-studies","published":"2010-09-02","volume":"157","issue":"1","pages":"27-45","abstract":"","topics":["mind"],"si":null,"url":"https://doi.org/10.1007/s11098-010-9616-y"},{"doi":"10.1007/s11098-010-9603-3","title":"Perceptual entitlement and basic beliefs","authors":["Peter J. Graham"],"journal":"phil-studies","published":"2010-09-02","volume":"153","issue":"3","pages":"467-475","abstract":"","topics":["mind"],"si":null,"url":"https://doi.org/10.1007/s11098-010-9603-3"},{"doi":"10.1007/s11098-010-9610-4","title":"Norms of intentionality: norms that don’t guide","authors":["Benjamin W. Jarvis"],"journal":"phil-studies","published":"2010-09-01","volume":"157","issue":"1","pages":"1-25","abstract":"","topics":["mind"],"si":null,"url":"https://doi.org/10.1007/s11098-010-9610-4"},{"doi":"10.1007/s11098-010-9606-0","title":"Precis of perception and basic beliefs","authors":["Jack Lyons"],"journal":"phil-studies","published":"2010-09-01","volume":"153","issue":"3","pages":"443-446","abstract":"","topics":["mind"],"si":null,"url":"https://doi.org/10.1007/s11098-010-9606-0"},{"doi":"10.1007/s11098-010-9608-y","title":"Kripke’s metalinguistic apparatus and the analysis of definite descriptions","authors":["Edward Kanterian"],"journal":"phil-studies","published":"2010-08-31","volume":"156","issue":"3","pages":"363-387","abstract":"","topics":["language"],"si":null,"url":"https://doi.org/10.1007/s11098-010-9608-y"},{"doi":"10.1007/s11098-010-9614-0","title":"Responses to Stoljar, Weatherson and Boghossian","authors":["Robert Stalnaker"],"journal":"phil-studies","published":"2010-08-31","volume":"155","issue":"3","pages":"467-479","abstract":"","topics":[],"si":null,"url":"https://doi.org/10.1007/s11098-010-9614-0"},{"doi":"10.1007/s11098-010-9615-z","title":"Précis","authors":["Robert Stalnaker"],"journal":"phil-studies","published":"2010-08-31","volume":"155","issue":"3","pages":"433-435","abstract":"","topics":[],"si":null,"url":"https://doi.org/10.1007/s11098-010-9615-z"},{"doi":"10.1007/s11098-010-9605-1","title":"Response to critics","authors":["Jack Lyons"],"journal":"phil-studies","published":"2010-08-31","volume":"153","issue":"3","pages":"477-488","abstract":"","topics":[],"si":null,"url":"https://doi.org/10.1007/s11098-010-9605-1"},{"doi":"10.1007/s11098-010-9607-z","title":"Spectrum inversion without a difference in representation is impossible","authors":["Jeff Speaks"],"journal":"phil-studies","published":"2010-08-29","volume":"156","issue":"3","pages":"339-361","abstract":"","topics":["mind"],"si":null,"url":"https://doi.org/10.1007/s11098-010-9607-z"},{"doi":"10.1007/s11098-010-9601-5","title":"In search of clarity about parity","authors":["Michael Wheeler"],"journal":"phil-studies","published":"2010-08-29","volume":"152","issue":"3","pages":"417-425","abstract":"","topics":[],"si":"Supersizing the Mind: Embodiment, Action, and Cognitive Extension (Oxford University Press, NY, 2008)","url":"https://doi.org/10.1007/s11098-010-9601-5"},{"doi":"10.1007/s11098-010-9596-y","title":"Deferentialism","authors":["Chris Daly","David Liggins"],"journal":"phil-studies","published":"2010-08-28","volume":"156","issue":"3","pages":"321-337","abstract":"","topics":[],"si":null,"url":"https://doi.org/10.1007/s11098-010-9596-y"},{"doi":"10.1007/s11098-010-9599-8","title":"Enculturating the Supersized Mind","authors":["Edwin Hutchins"],"journal":"phil-studies","published":"2010-08-27","volume":"152","issue":"3","pages":"437-446","abstract":"","topics":["mind"],"si":"Supersizing the Mind: Embodiment, Action, and Cognitive Extension (Oxford University Press, NY, 2008)","url":"https://doi.org/10.1007/s11098-010-9599-8"},{"doi":"10.1007/s11098-010-9602-4","title":"Commentary on Jack Lyons’s Perception and Basic Beliefs","authors":["Alvin I. Goldman"],"journal":"phil-studies","published":"2010-08-26","volume":"153","issue":"3","pages":"457-466","abstract":"","topics":["mind"],"si":null,"url":"https://doi.org/10.1007/s11098-010-9602-4"},{"doi":"10.1007/s11098-010-9600-6","title":"Cognitive systems and the supersized mind","authors":["Robert D. Rupert"],"journal":"phil-studies","published":"2010-08-26","volume":"152","issue":"3","pages":"427-436","abstract":"","topics":["mind"],"si":"Supersizing the Mind: Embodiment, Action, and Cognitive Extension (Oxford University Press, NY, 2008)","url":"https://doi.org/10.1007/s11098-010-9600-6"},{"doi":"10.1007/s11098-010-9595-z","title":"Lucky agents, big and little: should size really matter?","authors":["David Blumenfeld"],"journal":"phil-studies","published":"2010-08-17","volume":"156","issue":"3","pages":"311-319","abstract":"","topics":[],"si":null,"url":"https://doi.org/10.1007/s11098-010-9595-z"},{"doi":"10.1007/s11098-010-9585-1","title":"Moral principles as moral dispositions","authors":["Luke Robinson"],"journal":"phil-studies","published":"2010-08-03","volume":"156","issue":"2","pages":"289-309","abstract":"","topics":["ethics","metaphysics"],"si":null,"url":"https://doi.org/10.1007/s11098-010-9585-1"},{"doi":"10.1007/s11098-010-9589-x","title":"Descriptivism, scope, and apparently empty names","authors":["Andrew Cullison","Ben Caplan"],"journal":"phil-studies","published":"2010-07-16","volume":"156","issue":"2","pages":"283-288","abstract":"","topics":["language"],"si":null,"url":"https://doi.org/10.1007/s11098-010-9589-x"},{"doi":"10.1007/s11098-010-9588-y","title":"“Assertion” and intentionality","authors":["Jason Stanley"],"journal":"phil-studies","published":"2010-07-15","volume":"151","issue":"1","pages":"87-113","abstract":"","topics":["language","mind"],"si":null,"url":"https://doi.org/10.1007/s11098-010-9588-y"},{"doi":"10.1007/s11098-010-9580-6","title":"Tye-dyed teleology and the inverted spectrum","authors":["Jason Ford"],"journal":"phil-studies","published":"2010-07-14","volume":"156","issue":"2","pages":"267-281","abstract":"","topics":[],"si":null,"url":"https://doi.org/10.1007/s11098-010-9580-6"},{"doi":"10.1007/s11098-010-9590-4","title":"What is the Grounding Problem?","authors":["Louis deRosset"],"journal":"phil-studies","published":"2010-07-13","volume":"156","issue":"2","pages":"173-197","abstract":"","topics":["metaphysics"],"si":null,"url":"https://doi.org/10.1007/s11098-010-9590-4"},{"doi":"10.1007/s11098-010-9586-0","title":"Local contexts and local meanings","authors":["Philippe Schlenker"],"journal":"phil-studies","published":"2010-07-13","volume":"151","issue":"1","pages":"115-142","abstract":"","topics":[],"si":null,"url":"https://doi.org/10.1007/s11098-010-9586-0"},{"doi":"10.1007/s11098-010-9591-3","title":"Inconsistency in the A-Theory","authors":["Nicholas J. J. Smith"],"journal":"phil-studies","published":"2010-07-13","volume":"156","issue":"2","pages":"231-247","abstract":"","topics":[],"si":null,"url":"https://doi.org/10.1007/s11098-010-9591-3"},{"doi":"10.1007/s11098-010-9583-3","title":"Farewell to the luck (and Mind) argument","authors":["Christopher Evan Franklin"],"journal":"phil-studies","published":"2010-07-13","volume":"156","issue":"2","pages":"199-230","abstract":"","topics":["epistemology","mind"],"si":null,"url":"https://doi.org/10.1007/s11098-010-9583-3"},{"doi":"10.1007/s11098-010-9594-0","title":"The explanatory power of local miracle compatibilism","authors":["Garrett Pendergraft"],"journal":"phil-studies","published":"2010-07-13","volume":"156","issue":"2","pages":"249-266","abstract":"","topics":["religion"],"si":null,"url":"https://doi.org/10.1007/s11098-010-9594-0"},{"doi":"10.1007/s11098-010-9593-1","title":"Shallow versus deep response-dependence","authors":["Andrew William Howat"],"journal":"phil-studies","published":"2010-07-11","volume":"156","issue":"2","pages":"155-172","abstract":"","topics":[],"si":null,"url":"https://doi.org/10.1007/s11098-010-9593-1"},{"doi":"10.1007/s11098-010-9582-4","title":"Expressivism, representation, and the nature of conceptual analysis","authors":["David Plunkett"],"journal":"phil-studies","published":"2010-07-08","volume":"156","issue":"1","pages":"15-31","abstract":"","topics":["metaphil","mind"],"si":null,"url":"https://doi.org/10.1007/s11098-010-9582-4"},{"doi":"10.1007/s11098-010-9587-z","title":"Responses to Stanley and Schlenker","authors":["Robert Stalnaker"],"journal":"phil-studies","published":"2010-07-08","volume":"151","issue":"1","pages":"143-157","abstract":"","topics":[],"si":null,"url":"https://doi.org/10.1007/s11098-010-9587-z"},{"doi":"10.1007/s11098-010-9581-5","title":"Possible disagreements and defeat","authors":["Brandon Carey"],"journal":"phil-studies","published":"2010-07-07","volume":"155","issue":"3","pages":"371-381","abstract":"","topics":["epistemology"],"si":null,"url":"https://doi.org/10.1007/s11098-010-9581-5"},{"doi":"10.1007/s11098-010-9577-1","title":"The metaphysics of rule-following","authors":["Markus E. Schlosser"],"journal":"phil-studies","published":"2010-07-07","volume":"155","issue":"3","pages":"345-369","abstract":"","topics":["metaphysics","philsci"],"si":null,"url":"https://doi.org/10.1007/s11098-010-9577-1"},{"doi":"10.1007/s11098-010-9579-z","title":"Morality, reasons, and sentiments","authors":["Eric Vogelstein"],"journal":"phil-studies","published":"2010-07-07","volume":"155","issue":"3","pages":"421-432","abstract":"","topics":["ethics"],"si":null,"url":"https://doi.org/10.1007/s11098-010-9579-z"},{"doi":"10.1007/s11098-010-9578-0","title":"Concerning the resilience of Galen Strawson’s Basic Argument","authors":["Michael Anthony Istvan"],"journal":"phil-studies","published":"2010-07-07","volume":"155","issue":"3","pages":"399-420","abstract":"","topics":[],"si":null,"url":"https://doi.org/10.1007/s11098-010-9578-0"},{"doi":"10.1007/s11098-010-9576-2","title":"Quantifiers and epistemic contextualism","authors":["Jonathan Ichikawa"],"journal":"phil-studies","published":"2010-07-07","volume":"155","issue":"3","pages":"383-398","abstract":"","topics":["epistemology","logic"],"si":null,"url":"https://doi.org/10.1007/s11098-010-9576-2"},{"doi":"10.1007/s11098-010-9584-2","title":"Phenomenal conservatism and self-defeat: a reply to DePoe","authors":["Michael Huemer"],"journal":"phil-studies","published":"2010-07-06","volume":"156","issue":"1","pages":"1-13","abstract":"","topics":["mind"],"si":null,"url":"https://doi.org/10.1007/s11098-010-9584-2"},{"doi":"10.1007/s11098-010-9575-3","title":"On the meaning of the question “How fast does time pass?”","authors":["Bradford Skow"],"journal":"phil-studies","published":"2010-06-06","volume":"155","issue":"3","pages":"325-344","abstract":"","topics":["language","metaphysics"],"si":null,"url":"https://doi.org/10.1007/s11098-010-9575-3"},{"doi":"10.1007/s11098-010-9574-4","title":"Responsibility for necessities","authors":["Stephen Kearns"],"journal":"phil-studies","published":"2010-06-05","volume":"155","issue":"2","pages":"307-324","abstract":"","topics":["ethics"],"si":null,"url":"https://doi.org/10.1007/s11098-010-9574-4"},{"doi":"10.1007/s11098-010-9570-8","title":"A functional view of artistic evaluation","authors":["Jonathan Gilmore"],"journal":"phil-studies","published":"2010-06-03","volume":"155","issue":"2","pages":"289-305","abstract":"","topics":[],"si":null,"url":"https://doi.org/10.1007/s11098-010-9570-8"},{"doi":"10.1007/s11098-010-9572-6","title":"Disagreements about taste","authors":["Timothy Sundell"],"journal":"phil-studies","published":"2010-06-01","volume":"155","issue":"2","pages":"267-288","abstract":"","topics":["epistemology"],"si":null,"url":"https://doi.org/10.1007/s11098-010-9572-6"},{"doi":"10.1007/s11098-010-9563-7","title":"The symmetry of rational requirements","authors":["Jonathan Way"],"journal":"phil-studies","published":"2010-05-25","volume":"155","issue":"2","pages":"227-239","abstract":"","topics":[],"si":null,"url":"https://doi.org/10.1007/s11098-010-9563-7"},{"doi":"10.1007/s11098-010-9566-4","title":"The feels good theory of pleasure","authors":["Aaron Smuts"],"journal":"phil-studies","published":"2010-05-25","volume":"155","issue":"2","pages":"241-265","abstract":"","topics":[],"si":null,"url":"https://doi.org/10.1007/s11098-010-9566-4"},{"doi":"10.1007/s11098-010-9558-4","title":"On the supposed limits of physicalist theories of mind","authors":["Jonathan E. Dorsey"],"journal":"phil-studies","published":"2010-05-23","volume":"155","issue":"2","pages":"207-225","abstract":"","topics":["mind"],"si":null,"url":"https://doi.org/10.1007/s11098-010-9558-4"},{"doi":"10.1007/s11098-010-9573-5","title":"In defense of the mirror thesis","authors":["Peter Brian Barry"],"journal":"phil-studies","published":"2010-05-22","volume":"155","issue":"2","pages":"199-205","abstract":"","topics":[],"si":null,"url":"https://doi.org/10.1007/s11098-010-9573-5"},{"doi":"10.1007/s11098-010-9568-2","title":"Are there a posteriori conceptual necessities?","authors":["Daniel Dohrn"],"journal":"phil-studies","published":"2010-05-21","volume":"155","issue":"2","pages":"181-197","abstract":"","topics":[],"si":null,"url":"https://doi.org/10.1007/s11098-010-9568-2"},{"doi":"10.1007/s11098-010-9559-3","title":"Logic for morals, morals from logic","authors":["Charlie Kurth"],"journal":"phil-studies","published":"2010-05-20","volume":"155","issue":"2","pages":"161-180","abstract":"","topics":["ethics","logic"],"si":null,"url":"https://doi.org/10.1007/s11098-010-9559-3"},{"doi":"10.1007/s11098-010-9569-1","title":"Supervenience arguments under relaxed assumptions","authors":["Johannes Schmitt","Mark Schroeder"],"journal":"phil-studies","published":"2010-05-18","volume":"155","issue":"1","pages":"133-160","abstract":"","topics":[],"si":null,"url":"https://doi.org/10.1007/s11098-010-9569-1"},{"doi":"10.1007/s11098-010-9562-8","title":"Analog and digital, continuous and discrete","authors":["Corey J. Maley"],"journal":"phil-studies","published":"2010-05-18","volume":"155","issue":"1","pages":"117-131","abstract":"","topics":["tech-ai"],"si":null,"url":"https://doi.org/10.1007/s11098-010-9562-8"},{"doi":"10.1007/s11098-010-9560-x","title":"Reductive explanation, concepts, and a priori entailment","authors":["E. Diaz-Leon"],"journal":"phil-studies","published":"2010-05-15","volume":"155","issue":"1","pages":"99-116","abstract":"","topics":["philsci"],"si":null,"url":"https://doi.org/10.1007/s11098-010-9560-x"},{"doi":"10.1007/s11098-010-9565-5","title":"How to prove that some acts are wrong (without using substantive moral premises)","authors":["Christian Coons"],"journal":"phil-studies","published":"2010-05-14","volume":"155","issue":"1","pages":"83-98","abstract":"","topics":["ethics"],"si":null,"url":"https://doi.org/10.1007/s11098-010-9565-5"},{"doi":"10.1007/s11098-010-9522-3","title":"Hylemorphic animalism","authors":["Patrick Toner"],"journal":"phil-studies","published":"2010-05-14","volume":"155","issue":"1","pages":"65-81","abstract":"","topics":[],"si":null,"url":"https://doi.org/10.1007/s11098-010-9522-3"},{"doi":"10.1007/s11098-010-9571-7","title":"Methodology in aesthetics: the case of musical expressivity","authors":["Erkki Huovinen","Tobias Pontara"],"journal":"phil-studies","published":"2010-05-13","volume":"155","issue":"1","pages":"45-64","abstract":"","topics":["aesthetics"],"si":null,"url":"https://doi.org/10.1007/s11098-010-9571-7"},{"doi":"10.1007/s11098-010-9521-4","title":"Independence accounts of substance and substantial parts","authors":["Patrick Toner"],"journal":"phil-studies","published":"2010-05-13","volume":"155","issue":"1","pages":"37-43","abstract":"","topics":[],"si":null,"url":"https://doi.org/10.1007/s11098-010-9521-4"},{"doi":"10.1007/s11098-010-9564-6","title":"There is a problem of change","authors":["Michael J. Raven"],"journal":"phil-studies","published":"2010-05-12","volume":"155","issue":"1","pages":"23-35","abstract":"","topics":[],"si":null,"url":"https://doi.org/10.1007/s11098-010-9564-6"},{"doi":"10.1007/s11098-010-9561-9","title":"A new look at the problem of rule-following: a generic perspective","authors":["Kai-Yuan Cheng"],"journal":"phil-studies","published":"2010-05-12","volume":"155","issue":"1","pages":"1-21","abstract":"","topics":[],"si":null,"url":"https://doi.org/10.1007/s11098-010-9561-9"},{"doi":"10.1007/s11098-010-9567-3","title":"Misrepresenting consciousness","authors":["Josh Weisberg"],"journal":"phil-studies","published":"2010-05-12","volume":"154","issue":"3","pages":"409-433","abstract":"","topics":["mind"],"si":null,"url":"https://doi.org/10.1007/s11098-010-9567-3"},{"doi":"10.1007/s11098-010-9557-5","title":"Some groundwork for a multidimensional axiology","authors":["Alan Carter"],"journal":"phil-studies","published":"2010-05-07","volume":"154","issue":"3","pages":"389-408","abstract":"","topics":[],"si":null,"url":"https://doi.org/10.1007/s11098-010-9557-5"},{"doi":"10.1007/s11098-010-9550-z","title":"Comments on Ralph Wedgwood’s The Nature of Normativity","authors":["Richard Holton"],"journal":"phil-studies","published":"2010-04-29","volume":"151","issue":"3","pages":"449-457","abstract":"","topics":["ethics"],"si":null,"url":"https://doi.org/10.1007/s11098-010-9550-z"},{"doi":"10.1007/s11098-010-9525-0","title":"Minimal authorship (of sorts)","authors":["Christy Mag Uidhir"],"journal":"phil-studies","published":"2010-04-29","volume":"154","issue":"3","pages":"373-387","abstract":"","topics":[],"si":null,"url":"https://doi.org/10.1007/s11098-010-9525-0"},{"doi":"10.1007/s11098-010-9556-6","title":"What must a proof of incompatibilism prove?","authors":["Seth Shabo"],"journal":"phil-studies","published":"2010-04-28","volume":"154","issue":"3","pages":"361-371","abstract":"","topics":["logic"],"si":null,"url":"https://doi.org/10.1007/s11098-010-9556-6"},{"doi":"10.1007/s11098-010-9555-7","title":"No pairing problem","authors":["Andrew M. Bailey","Joshua Rasmussen","Luke Van Horn"],"journal":"phil-studies","published":"2010-04-22","volume":"154","issue":"3","pages":"349-360","abstract":"","topics":[],"si":null,"url":"https://doi.org/10.1007/s11098-010-9555-7"},{"doi":"10.1007/s11098-010-9551-y","title":"Staying in touch with normative reality","authors":["Peter Railton"],"journal":"phil-studies","published":"2010-04-20","volume":"151","issue":"3","pages":"459-467","abstract":"","topics":["ethics"],"si":null,"url":"https://doi.org/10.1007/s11098-010-9551-y"},{"doi":"10.1007/s11098-010-9552-x","title":"Uggles and Muggles: Wedgwood on normative thought and justification","authors":["James Lenman"],"journal":"phil-studies","published":"2010-04-10","volume":"151","issue":"3","pages":"469-477","abstract":"","topics":["epistemology","ethics"],"si":null,"url":"https://doi.org/10.1007/s11098-010-9552-x"},{"doi":"10.1007/s11098-010-9553-9","title":"The Nature of Normativity: Précis","authors":["Ralph Wedgwood"],"journal":"phil-studies","published":"2010-04-08","volume":"151","issue":"3","pages":"445-448","abstract":"","topics":["ethics"],"si":null,"url":"https://doi.org/10.1007/s11098-010-9553-9"},{"doi":"10.1007/s11098-010-9549-5","title":"Reply to Belot, Elgin, and Horsten","authors":["Bas C. van Fraassen"],"journal":"phil-studies","published":"2010-04-08","volume":"150","issue":"3","pages":"461-472","abstract":"","topics":[],"si":null,"url":"https://doi.org/10.1007/s11098-010-9549-5"},{"doi":"10.1007/s11098-010-9554-8","title":"The Nature of Normativity: A Reply to Holton, Railton, and Lenman","authors":["Ralph Wedgwood"],"journal":"phil-studies","published":"2010-04-08","volume":"151","issue":"3","pages":"479-491","abstract":"","topics":["ethics"],"si":null,"url":"https://doi.org/10.1007/s11098-010-9554-8"},{"doi":"10.1007/s11098-010-9548-6","title":"Having an interpretation","authors":["Leon Horsten"],"journal":"phil-studies","published":"2010-04-07","volume":"150","issue":"3","pages":"449-459","abstract":"","topics":[],"si":null,"url":"https://doi.org/10.1007/s11098-010-9548-6"},{"doi":"10.1007/s11098-010-9546-8","title":"Transcendental idealism among the Jersey metaphysicians","authors":["Gordon Belot"],"journal":"phil-studies","published":"2010-04-07","volume":"150","issue":"3","pages":"429-438","abstract":"","topics":["metaphysics"],"si":null,"url":"https://doi.org/10.1007/s11098-010-9546-8"},{"doi":"10.1007/s11098-010-9534-z","title":"Are normative properties descriptive properties?","authors":["Bart Streumer"],"journal":"phil-studies","published":"2010-04-06","volume":"154","issue":"3","pages":"325-348","abstract":"","topics":["ethics"],"si":null,"url":"https://doi.org/10.1007/s11098-010-9534-z"},{"doi":"10.1007/s11098-010-9543-y","title":"Coreference and meaning","authors":["N. Ángel Pinillos"],"journal":"phil-studies","published":"2010-04-04","volume":"154","issue":"2","pages":"301-324","abstract":"","topics":["language"],"si":null,"url":"https://doi.org/10.1007/s11098-010-9543-y"},{"doi":"10.1007/s11098-010-9545-9","title":"Precis of Scientific representation: paradoxes of perspective","authors":["Bas C. van Fraassen"],"journal":"phil-studies","published":"2010-04-04","volume":"150","issue":"3","pages":"425-428","abstract":"","topics":["logic","mind","philsci"],"si":null,"url":"https://doi.org/10.1007/s11098-010-9545-9"},{"doi":"10.1007/s11098-010-9538-8","title":"Getting priority straight","authors":["Louis deRosset"],"journal":"phil-studies","published":"2010-04-03","volume":"149","issue":"1","pages":"73-97","abstract":"","topics":[],"si":null,"url":"https://doi.org/10.1007/s11098-010-9538-8"},{"doi":"10.1007/s11098-010-9541-0","title":"Tell me you love me: bootstrapping, externalism, and no-lose epistemology","authors":["Michael G. Titelbaum"],"journal":"phil-studies","published":"2010-04-02","volume":"149","issue":"1","pages":"119-134","abstract":"","topics":["epistemology"],"si":null,"url":"https://doi.org/10.1007/s11098-010-9541-0"},{"doi":"10.1007/s11098-010-9547-7","title":"Keeping things in perspective","authors":["Catherine Z. Elgin"],"journal":"phil-studies","published":"2010-04-01","volume":"150","issue":"3","pages":"439-447","abstract":"","topics":[],"si":null,"url":"https://doi.org/10.1007/s11098-010-9547-7"},{"doi":"10.1007/s11098-010-9544-x","title":"Does knowledge secure warrant to assert?","authors":["E. J. Coffman"],"journal":"phil-studies","published":"2010-03-31","volume":"154","issue":"2","pages":"285-300","abstract":"","topics":["epistemology"],"si":null,"url":"https://doi.org/10.1007/s11098-010-9544-x"},{"doi":"10.1007/s11098-010-9537-9","title":"Why Leibniz thinks Descartes was wrong and the Scholastics were right","authors":["Tyler Doggett"],"journal":"phil-studies","published":"2010-03-27","volume":"149","issue":"1","pages":"1-18","abstract":"","topics":["history"],"si":null,"url":"https://doi.org/10.1007/s11098-010-9537-9"},{"doi":"10.1007/s11098-010-9542-z","title":"Assertion, knowledge, and action","authors":["Ishani Maitra","Brian Weatherson"],"journal":"phil-studies","published":"2010-03-23","volume":"149","issue":"1","pages":"99-118","abstract":"","topics":["action","epistemology","language"],"si":null,"url":"https://doi.org/10.1007/s11098-010-9542-z"},{"doi":"10.1007/s11098-010-9540-1","title":"The particularity and phenomenology of perceptual experience","authors":["Susanna Schellenberg"],"journal":"phil-studies","published":"2010-03-23","volume":"149","issue":"1","pages":"19-48","abstract":"","topics":["mind"],"si":null,"url":"https://doi.org/10.1007/s11098-010-9540-1"},{"doi":"10.1007/s11098-010-9536-x","title":"Truth and meaning redux","authors":["Ernie Lepore","Kirk Ludwig"],"journal":"phil-studies","published":"2010-03-20","volume":"154","issue":"2","pages":"251-277","abstract":"","topics":["language"],"si":null,"url":"https://doi.org/10.1007/s11098-010-9536-x"},{"doi":"10.1007/s11098-010-9539-7","title":"Binding and its consequences","authors":["Christopher J. G. Meacham"],"journal":"phil-studies","published":"2010-03-19","volume":"149","issue":"1","pages":"49-71","abstract":"","topics":[],"si":null,"url":"https://doi.org/10.1007/s11098-010-9539-7"},{"doi":"10.1007/s11098-010-9523-2","title":"Sider, Hawley, Sider and the Vagueness Argument","authors":["Nikk Effingham"],"journal":"phil-studies","published":"2010-03-16","volume":"154","issue":"2","pages":"241-250","abstract":"","topics":[],"si":null,"url":"https://doi.org/10.1007/s11098-010-9523-2"},{"doi":"10.1007/s11098-010-9535-y","title":"Against quietist normative realism","authors":["Tristram McPherson"],"journal":"phil-studies","published":"2010-03-11","volume":"154","issue":"2","pages":"223-240","abstract":"","topics":["ethics","metaphysics"],"si":null,"url":"https://doi.org/10.1007/s11098-010-9535-y"},{"doi":"10.1007/s11098-010-9531-2","title":"How to count people","authors":["Mark Bajakian"],"journal":"phil-studies","published":"2010-03-09","volume":"154","issue":"2","pages":"185-204","abstract":"","topics":[],"si":null,"url":"https://doi.org/10.1007/s11098-010-9531-2"},{"doi":"10.1007/s11098-010-9532-1","title":"Singular thoughts and singular propositions","authors":["Joshua Armstrong","Jason Stanley"],"journal":"phil-studies","published":"2010-03-09","volume":"154","issue":"2","pages":"205-222","abstract":"","topics":["language"],"si":null,"url":"https://doi.org/10.1007/s11098-010-9532-1"},{"doi":"10.1007/s11098-010-9533-0","title":"Internalism about a person’s good: don’t believe it","authors":["Alexander Sarch"],"journal":"phil-studies","published":"2010-03-06","volume":"154","issue":"2","pages":"161-184","abstract":"","topics":["epistemology"],"si":null,"url":"https://doi.org/10.1007/s11098-010-9533-0"},{"doi":"10.1007/s11098-010-9526-z","title":"Endurantist and perdurantist accounts of persistence","authors":["Maureen Donnelly"],"journal":"phil-studies","published":"2010-03-05","volume":"154","issue":"1","pages":"27-51","abstract":"","topics":["metaphysics"],"si":null,"url":"https://doi.org/10.1007/s11098-010-9526-z"},{"doi":"10.1007/s11098-010-9507-2","title":"Heated agreement: Lack of Character as Being for the Good","authors":["John M. Doris"],"journal":"phil-studies","published":"2010-03-01","volume":"148","issue":"1","pages":"135-146","abstract":"","topics":[],"si":null,"url":"https://doi.org/10.1007/s11098-010-9507-2"},{"doi":"10.1007/s11098-010-9530-3","title":"Replies to my critics","authors":["Edouard Machery"],"journal":"phil-studies","published":"2010-02-27","volume":"149","issue":"3","pages":"429-436","abstract":"","topics":[],"si":null,"url":"https://doi.org/10.1007/s11098-010-9530-3"},{"doi":"10.1007/s11098-010-9529-9","title":"Can we do without concepts?: Comments on Edouard Machery, Doing Without Concepts","authors":["Diana Raffman"],"journal":"phil-studies","published":"2010-02-27","volume":"149","issue":"3","pages":"423-427","abstract":"","topics":[],"si":null,"url":"https://doi.org/10.1007/s11098-010-9529-9"},{"doi":"10.1007/s11098-010-9517-0","title":"Moorean responses to skepticism: a defense","authors":["Tim Willenken"],"journal":"phil-studies","published":"2010-02-27","volume":"154","issue":"1","pages":"1-25","abstract":"","topics":["epistemology"],"si":null,"url":"https://doi.org/10.1007/s11098-010-9517-0"},{"doi":"10.1007/s11098-010-9519-y","title":"The chameleon’s revenge: Response-dependence, finks and provisoed biconditionals","authors":["Eline Busck Gundersen"],"journal":"phil-studies","published":"2010-02-25","volume":"153","issue":"3","pages":"435-441","abstract":"","topics":[],"si":null,"url":"https://doi.org/10.1007/s11098-010-9519-y"},{"doi":"10.1007/s11098-010-9516-1","title":"The logic of ‘being informed’ revisited and revised","authors":["Patrick Allo"],"journal":"phil-studies","published":"2010-02-24","volume":"153","issue":"3","pages":"417-434","abstract":"","topics":["logic"],"si":null,"url":"https://doi.org/10.1007/s11098-010-9516-1"},{"doi":"10.1007/s11098-010-9527-y","title":"Précis of Doing without Concepts","authors":["Edouard Machery"],"journal":"phil-studies","published":"2010-02-23","volume":"149","issue":"3","pages":"401-410","abstract":"","topics":[],"si":null,"url":"https://doi.org/10.1007/s11098-010-9527-y"},{"doi":"10.1007/s11098-010-9528-x","title":"I love Machery’s book, but love concepts more","authors":["Christopher S. Hill"],"journal":"phil-studies","published":"2010-02-21","volume":"149","issue":"3","pages":"411-421","abstract":"","topics":[],"si":null,"url":"https://doi.org/10.1007/s11098-010-9528-x"},{"doi":"10.1007/s11098-010-9518-z","title":"Second-order properties and three varieties of functionalism","authors":["Eric Hiddleston"],"journal":"phil-studies","published":"2010-02-20","volume":"153","issue":"3","pages":"397-415","abstract":"","topics":[],"si":null,"url":"https://doi.org/10.1007/s11098-010-9518-z"},{"doi":"10.1007/s11098-010-9514-3","title":"Realizing what might be","authors":["Malte Willer"],"journal":"phil-studies","published":"2010-02-18","volume":"153","issue":"3","pages":"365-375","abstract":"","topics":[],"si":null,"url":"https://doi.org/10.1007/s11098-010-9514-3"},{"doi":"10.1007/s11098-010-9524-1","title":"Mind–brain identity and evidential insulation","authors":["Jakob Hohwy"],"journal":"phil-studies","published":"2010-02-18","volume":"153","issue":"3","pages":"377-395","abstract":"","topics":["epistemology","mind"],"si":null,"url":"https://doi.org/10.1007/s11098-010-9524-1"},{"doi":"10.1007/s11098-010-9520-5","title":"Van Inwagen’s modal skepticism","authors":["Peter Hawke"],"journal":"phil-studies","published":"2010-02-16","volume":"153","issue":"3","pages":"351-364","abstract":"","topics":["epistemology"],"si":null,"url":"https://doi.org/10.1007/s11098-010-9520-5"},{"doi":"10.1007/s11098-010-9505-4","title":"The subjective intuition","authors":["Jennifer S. Hawkins"],"journal":"phil-studies","published":"2010-02-13","volume":"148","issue":"1","pages":"61-68","abstract":"","topics":["metaphil"],"si":null,"url":"https://doi.org/10.1007/s11098-010-9505-4"},{"doi":"10.1007/s11098-010-9515-2","title":"Unanswerable questions for Millians","authors":["Ilhan Inan"],"journal":"phil-studies","published":"2010-02-11","volume":"154","issue":"2","pages":"279-283","abstract":"","topics":[],"si":null,"url":"https://doi.org/10.1007/s11098-010-9515-2"},{"doi":"10.1007/s11098-010-9509-0","title":"Locating projectivism in intentionalism debates","authors":["Derek H. Brown"],"journal":"phil-studies","published":"2010-02-07","volume":"148","issue":"1","pages":"69-78","abstract":"","topics":[],"si":null,"url":"https://doi.org/10.1007/s11098-010-9509-0"},{"doi":"10.1007/s11098-010-9513-4","title":"Moorean pluralism as a solution to the incommensurability problem","authors":["Justin Klocksiem"],"journal":"phil-studies","published":"2010-02-04","volume":"153","issue":"3","pages":"335-349","abstract":"","topics":[],"si":null,"url":"https://doi.org/10.1007/s11098-010-9513-4"},{"doi":"10.1007/s11098-010-9510-7","title":"Realization theory and the philosophy of mind: comments on Sydney Shoemaker’s physical realization","authors":["Louise Antony"],"journal":"phil-studies","published":"2010-02-04","volume":"148","issue":"1","pages":"89-99","abstract":"","topics":["mind"],"si":null,"url":"https://doi.org/10.1007/s11098-010-9510-7"},{"doi":"10.1007/s11098-010-9506-3","title":"Editorial","authors":["Paul Hurley"],"journal":"phil-studies","published":"2010-02-04","volume":"148","issue":"1","pages":"1-1","abstract":"","topics":[],"si":null,"url":"https://doi.org/10.1007/s11098-010-9506-3"},{"doi":"10.1007/s11098-010-9502-7","title":"How to take skepticism seriously","authors":["Adam Leite"],"journal":"phil-studies","published":"2010-02-02","volume":"148","issue":"1","pages":"39-60","abstract":"","topics":["epistemology"],"si":null,"url":"https://doi.org/10.1007/s11098-010-9502-7"},{"doi":"10.1007/s11098-010-9508-1","title":"Recollection, perception, imagination","authors":["Alex Byrne"],"journal":"phil-studies","published":"2010-01-29","volume":"148","issue":"1","pages":"15-26","abstract":"","topics":["aesthetics","mind"],"si":null,"url":"https://doi.org/10.1007/s11098-010-9508-1"},{"doi":"10.1007/s11098-010-9497-0","title":"The pursuit of the natural","authors":["Scott Tanona"],"journal":"phil-studies","published":"2010-01-28","volume":"148","issue":"1","pages":"79-87","abstract":"","topics":[],"si":null,"url":"https://doi.org/10.1007/s11098-010-9497-0"},{"doi":"10.1007/s11098-010-9512-5","title":"A theory of virtue: response to critics","authors":["Robert Merrihew Adams"],"journal":"phil-studies","published":"2010-01-28","volume":"148","issue":"1","pages":"159-165","abstract":"","topics":["ethics"],"si":null,"url":"https://doi.org/10.1007/s11098-010-9512-5"},{"doi":"10.1007/s11098-010-9504-5","title":"Comments on Robert Adams, A theory of virtue: excellence in being for the good","authors":["Rachana Kamtekar"],"journal":"phil-studies","published":"2010-01-26","volume":"148","issue":"1","pages":"147-158","abstract":"","topics":["ethics"],"si":null,"url":"https://doi.org/10.1007/s11098-010-9504-5"},{"doi":"10.1007/s11098-010-9511-6","title":"A theory of virtue: introductory remarks","authors":["Robert Merrihew Adams"],"journal":"phil-studies","published":"2010-01-26","volume":"148","issue":"1","pages":"133-134","abstract":"","topics":["ethics"],"si":null,"url":"https://doi.org/10.1007/s11098-010-9511-6"},{"doi":"10.1007/s11098-010-9503-6","title":"Thoughts on Sydney Shoemaker’s Physical Realization","authors":["Jaegwon Kim"],"journal":"phil-studies","published":"2010-01-26","volume":"148","issue":"1","pages":"101-112","abstract":"","topics":[],"si":null,"url":"https://doi.org/10.1007/s11098-010-9503-6"},{"doi":"10.1007/s11098-010-9498-z","title":"Observer perspective and acentred memory: some puzzles about point of view in personal memory","authors":["John Sutton"],"journal":"phil-studies","published":"2010-01-23","volume":"148","issue":"1","pages":"27-37","abstract":"","topics":["mind"],"si":null,"url":"https://doi.org/10.1007/s11098-010-9498-z"},{"doi":"10.1007/s11098-010-9499-y","title":"Reply to my critics","authors":["Sydney Shoemaker"],"journal":"phil-studies","published":"2010-01-23","volume":"148","issue":"1","pages":"125-132","abstract":"","topics":[],"si":null,"url":"https://doi.org/10.1007/s11098-010-9499-y"},{"doi":"10.1007/s11098-010-9500-9","title":"Comments on Sydney Shoemaker’s Physical Realization","authors":["Andrew Melnyk"],"journal":"phil-studies","published":"2010-01-23","volume":"148","issue":"1","pages":"113-123","abstract":"","topics":[],"si":null,"url":"https://doi.org/10.1007/s11098-010-9500-9"},{"doi":"10.1007/s11098-010-9501-8","title":"Is memory preservation?","authors":["Mohan Matthen"],"journal":"phil-studies","published":"2010-01-22","volume":"148","issue":"1","pages":"3-14","abstract":"","topics":["mind"],"si":null,"url":"https://doi.org/10.1007/s11098-010-9501-8"},{"doi":"10.1007/s11098-010-9495-2","title":"The nature of intuitive justification","authors":["Elijah Chudnoff"],"journal":"phil-studies","published":"2010-01-20","volume":"153","issue":"2","pages":"313-333","abstract":"","topics":["epistemology"],"si":null,"url":"https://doi.org/10.1007/s11098-010-9495-2"},{"doi":"10.1007/s11098-010-9496-1","title":"A paradox for supertask decision makers","authors":["Andrew Bacon"],"journal":"phil-studies","published":"2010-01-19","volume":"153","issue":"2","pages":"307-311","abstract":"","topics":["logic"],"si":null,"url":"https://doi.org/10.1007/s11098-010-9496-1"},{"doi":"10.1007/s11098-010-9494-3","title":"Expectancy and rational action prior to personal fission","authors":["Paul Tappenden"],"journal":"phil-studies","published":"2010-01-12","volume":"153","issue":"2","pages":"299-306","abstract":"","topics":["action"],"si":null,"url":"https://doi.org/10.1007/s11098-010-9494-3"}]