[{"doi":"10.2307/2215811","title":"The Myth of the Essential Indexical","authors":["Ruth Garrett Millikan"],"journal":"nous","published":"1990-12-01","volume":"24","issue":"5","topics":["language"],"ha":false},{"doi":"10.1007/bf00484837","title":"Against conditionalization","authors":["F. Bacchus","H. E. Kyburg","M. Thalos"],"journal":"synthese","published":"1990-12-01","volume":"85","issue":"3","topics":["philsci"],"ha":false},{"doi":"10.1007/bf00484836","title":"The sorites paradox and higher-order vagueness","authors":["J. A. Burgess"],"journal":"synthese","published":"1990-12-01","volume":"85","issue":"3","topics":["logic","philsci"],"ha":false},{"doi":"10.1136/jme.16.4.187","title":"Why is preventive medicine exempted from ethical constraints?","authors":["P Skrabanek"],"journal":"jme","published":"1990-12-01","volume":"16","issue":"4","topics":["ethics","philsci"],"ha":true},{"doi":"10.1007/bf01883517","title":"Neumark's theorem and quantum inseparability","authors":["Asher Peres"],"journal":"found-phys","published":"1990-12-01","volume":"20","issue":"12","topics":["philsci"],"ha":false},{"doi":"10.1007/bf01883518","title":"Momentum spread: Amplitude and current contributions","authors":["Leon Cohen"],"journal":"found-phys","published":"1990-12-01","volume":"20","issue":"12","topics":["philsci"],"ha":false},{"doi":"10.1007/bf00717588","title":"The no-slip condition of fluid dynamics","authors":["Michael A. Day"],"journal":"erkenntnis","published":"1990-11-01","volume":"33","issue":"3","topics":["philsci"],"ha":false},{"doi":"10.1007/bf00717590","title":"The inference to the best explanation","authors":["Yemima Ben-Menahem"],"journal":"erkenntnis","published":"1990-11-01","volume":"33","issue":"3","topics":["logic","philsci"],"ha":false},{"doi":"10.1017/s0953820800000704","title":"Jevons's Applications of Utilitarian Theory to Economic Policy","authors":["Sandra J. Peart"],"journal":"utilitas","published":"1990-11-01","volume":"2","issue":"2","topics":["ethics"],"ha":true},{"doi":"10.1111/j.1467-9973.1990.tb00541.x","title":"DO CHILDREN THINK PHILOSOPHICALLY?1","authors":["RICHARD F. KITCHENER"],"journal":"metaphilosophy","published":"1990-10-01","volume":"21","issue":"4","ha":false},{"doi":"10.1017/s0031819100064718","title":"Going Nowhere: Nagel on Normative Objectivity","authors":["Marilyn Friedman"],"journal":"philosophy","published":"1990-10-01","volume":"65","issue":"254","topics":["action","epistemology","ethics"],"ha":true},{"doi":"10.1017/s003181910006469x","title":"Aristotle on Dialectic","authors":["D. W. Hamlyn"],"journal":"philosophy","published":"1990-10-01","volume":"65","issue":"254","topics":["history"],"ha":true},{"doi":"10.1086/293257","title":"Internalism and Speaker Relativism","authors":["James Dreier"],"journal":"ethics","published":"1990-10-01","volume":"101","issue":"1","topics":["epistemology","ethics"],"ha":false},{"doi":"10.1086/293261","title":"Justifying the State","authors":["David Schmidtz"],"journal":"ethics","published":"1990-10-01","volume":"101","issue":"1","topics":["ethics"],"ha":false},{"doi":"10.1086/293259","title":"The Misfortunes of Virtue","authors":["J. B. Schneewind"],"journal":"ethics","published":"1990-10-01","volume":"101","issue":"1","topics":["ethics"],"ha":false},{"doi":"10.1086/293258","title":"Moral Conflicts and Ethical Relativism","authors":["Judith Wagner DeCew"],"journal":"ethics","published":"1990-10-01","volume":"101","issue":"1","topics":["ethics"],"ha":false},{"doi":"10.1017/s0266267100001255","title":"Keynesian Uncertainty and the Weight of Arguments","authors":["Jochen Runde"],"journal":"econ-phil","published":"1990-10-01","volume":"6","issue":"2","topics":["ethics","philsci"],"ha":true},{"doi":"10.1017/s0266267100001218","title":"The Ethical Limitations of the Market","authors":["Elizabeth Anderson"],"journal":"econ-phil","published":"1990-10-01","volume":"6","issue":"2","topics":["ethics"],"ha":true},{"doi":"10.1111/j.1468-5930.1990.tb00275.x","title":"Correspondence","authors":["Alan Haworth"],"journal":"jap","published":"1990-10-01","volume":"7","issue":"2","topics":["ethics"],"ha":false},{"doi":"10.1007/bf02207385","title":"David Hull's evolutionary model for the progress and process of science","authors":["David Oldroyd"],"journal":"bio-phil","published":"1990-10-01","volume":"5","issue":"4","topics":["philsci"],"ha":false},{"doi":"10.1007/bf02207384","title":"Sociology, selection, and success: A critique of David Hull's analysis of science and systematics","authors":["Michael J. Donoghue"],"journal":"bio-phil","published":"1990-10-01","volume":"5","issue":"4","topics":["philsci"],"ha":false},{"doi":"10.1007/bf01889466","title":"The zitterbewegung interpretation of quantum mechanics","authors":["David Hestenes"],"journal":"found-phys","published":"1990-10-01","volume":"20","issue":"10","topics":["philsci"],"ha":false},{"doi":"10.1007/bf00485186","title":"The structuralist view of mathematical objects","authors":["Charles Parsons"],"journal":"synthese","published":"1990-09-01","volume":"84","issue":"3","topics":["logic","philsci"],"ha":false},{"doi":"10.1080/00048409012344301","title":"Weakness of will and rational action","authors":["Robert Audi"],"journal":"ajp","published":"1990-09-01","volume":"68","issue":"3","topics":["action"],"ha":false},{"doi":"10.1007/bf00166332","title":"The intentional and the intended","authors":["J. L. A. Garcia"],"journal":"erkenntnis","published":"1990-09-01","volume":"33","issue":"2","topics":["action","philsci"],"ha":false},{"doi":"10.1080/00455091.1990.10716495","title":"True Contradictions","authors":["Terence Parsons"],"journal":"cjp","published":"1990-09-01","volume":"20","issue":"3","ha":true},{"doi":"10.1080/00455091.1990.10716494","title":"Is Mandatory Retirement Unfair Age Discrimination?","authors":["Gary A. Wedeking"],"journal":"cjp","published":"1990-09-01","volume":"20","issue":"3","ha":true},{"doi":"10.1016/0039-3681(90)90006-t","title":"Kuhn's conception of incommensurability","authors":["Paul Hoyningen-Huene"],"journal":"shps","published":"1990-09-01","volume":"21","issue":"3","topics":["philsci"],"ha":false},{"doi":"10.1007/bf00355744","title":"The basic notion of justification","authors":["Jonathan L. Kvanvig","Christopher Menzel"],"journal":"phil-studies","published":"1990-07-01","volume":"59","issue":"3","topics":["epistemology"],"ha":false},{"doi":"10.1007/bf00355747","title":"The explanatory role of belief ascriptions","authors":["Sarah Patterson"],"journal":"phil-studies","published":"1990-07-01","volume":"59","issue":"3","topics":["epistemology"],"ha":false},{"doi":"10.2307/2185347","title":"Truth Rules, Hoverflies, and the Kripke-Wittgenstein Paradox","authors":["Ruth Garrett Millikan"],"journal":"phil-review","published":"1990-07-01","volume":"99","issue":"3","topics":["history","logic"],"ha":false},{"doi":"10.1007/bf00634555","title":"Review","authors":["Robert Ackermann"],"journal":"erkenntnis","published":"1990-07-01","volume":"33","issue":"1","topics":["philsci"],"ha":false},{"doi":"10.2307/2219723","title":"Whose Language is it Anyway? Some Notes on Idiolects","authors":["Alexander George"],"journal":"pq","published":"1990-07-01","volume":"40","issue":"160","topics":["language"],"ha":false},{"doi":"10.1017/s0031819100057624","title":"A Kantian View of Moral Luck","authors":["A. W. Moore"],"journal":"philosophy","published":"1990-07-01","volume":"65","issue":"253","topics":["blame-resp","epistemology","ethics","history"],"ha":true},{"doi":"10.1007/bf00165254","title":"The real objective of Mendel's paper","authors":["Floyd V. Monaghan","Alain F. Corcos"],"journal":"bio-phil","published":"1990-07-01","volume":"5","issue":"3","topics":["philsci"],"ha":false},{"doi":"10.1007/bf00165257","title":"Genetic traits","authors":["Fred Gifford"],"journal":"bio-phil","published":"1990-07-01","volume":"5","issue":"3","topics":["philsci"],"ha":false},{"doi":"10.2307/2215774","title":"Primary Goods Reconsidered","authors":["Richard J. Arneson"],"journal":"nous","published":"1990-06-01","volume":"24","issue":"3","ha":false},{"doi":"10.1007/bf00368203","title":"The wall and the shield K-K reconsidered","authors":["Michael Roth"],"journal":"phil-studies","published":"1990-06-01","volume":"59","issue":"2","ha":false},{"doi":"10.1007/bf00413421","title":"Duhem in different contexts: Comments on Brenner and Martin","authors":["Philip L. Quinn"],"journal":"synthese","published":"1990-06-01","volume":"83","issue":"3","topics":["philsci"],"ha":false},{"doi":"10.1007/bf00413422","title":"Einstein and Duhem","authors":["Don Howard"],"journal":"synthese","published":"1990-06-01","volume":"83","issue":"3","topics":["philsci"],"ha":false},{"doi":"10.1007/bf00413426","title":"Comment: Duhem's middle way","authors":["Ernan McMullin"],"journal":"synthese","published":"1990-06-01","volume":"83","issue":"3","topics":["philsci"],"ha":false},{"doi":"10.1080/00048409012344161","title":"On the genuine queerness of moral properties and facts","authors":["Richard T. Garner"],"journal":"ajp","published":"1990-06-01","volume":"68","issue":"2","topics":["ethics"],"ha":false},{"doi":"10.1093/analys/50.3.182","title":"Fitch and intuitionistic knowability","authors":["P. Percival"],"journal":"analysis","published":"1990-06-01","volume":"50","issue":"3","ha":false},{"doi":"10.1093/bjps/41.2.147","title":"Scientific Instruments, Scientific Progress and the Cyclotron","authors":["DAVIS BAIRD","THOMAS FAUST"],"journal":"bjps","published":"1990-06-01","volume":"41","issue":"2","topics":["philsci"],"ha":false},{"doi":"10.1086/289543","title":"The Conceptual Structure of the Chemical Revolution","authors":["Paul Thagard"],"journal":"phil-sci","published":"1990-06-01","volume":"57","issue":"2","topics":["philsci","tech-ai"],"ha":true},{"doi":"10.1016/0039-3681(90)90022-z","title":"The anthropology of incommensurability","authors":["Mario Biagioli"],"journal":"shps","published":"1990-06-01","volume":"21","issue":"2","topics":["philsci"],"ha":false},{"doi":"10.1007/bf00368389","title":"Declaratives are not enough","authors":["Nuel Belnap"],"journal":"phil-studies","published":"1990-05-01","volume":"59","issue":"1","ha":false},{"doi":"10.1007/bf00413755","title":"Logical examination of physical theory","authors":["Pierre Duhem"],"journal":"synthese","published":"1990-05-01","volume":"83","issue":"2","topics":["logic","philsci"],"ha":false},{"doi":"10.2307/2026835","title":"Killing, Abortion, and Contraception: A Reply to Marquis","authors":["Alastair Norcross"],"journal":"jphil","published":"1990-05-01","volume":"87","issue":"5","ha":false},{"doi":"10.2307/2026834","title":"Does a Fetus Already have a Future-Like-Ours?","authors":["Peter K. McInerney"],"journal":"jphil","published":"1990-05-01","volume":"87","issue":"5","ha":false},{"doi":"10.2307/2215530","title":"Surviving Matters","authors":["Ernest Sosa"],"journal":"nous","published":"1990-04-01","volume":"24","issue":"2","ha":false},{"doi":"10.2307/2215526","title":"Symposia Papers: Four-Dimensional Objects","authors":["Peter van Inwagen"],"journal":"nous","published":"1990-04-01","volume":"24","issue":"2","ha":false},{"doi":"10.1007/bf00413686","title":"Explanation and the Language of Thought","authors":["David Braddon-Mitchell","John Fitzpatrick"],"journal":"synthese","published":"1990-04-01","volume":"83","issue":"1","topics":["language","philsci"],"ha":false},{"doi":"10.2307/2026681","title":"A Second Look at Pornography and The Subordination of Women","authors":["W. A. Parent"],"journal":"jphil","published":"1990-04-01","volume":"87","issue":"4","ha":false},{"doi":"10.1086/293210","title":"Equity Versus Efficiency: The Elusive Trade-Off","authors":["Julian Le Grand"],"journal":"ethics","published":"1990-04-01","volume":"100","issue":"3","topics":["ethics"],"ha":false},{"doi":"10.1007/bf01889640","title":"The role of “craft language” in learning “Waza”","authors":["Kumiko Ikuta"],"journal":"ai-soc","published":"1990-04-01","volume":"4","issue":"2","topics":["language","tech-ai"],"ha":false},{"doi":"10.2307/2215611","title":"Reason and Reflective Judgment: Kant on the Significance of Systematicity","authors":["Paul Guyer"],"journal":"nous","published":"1990-03-01","volume":"24","issue":"1","topics":["history"],"ha":false},{"doi":"10.2307/2215615","title":"The Objectivity of Taste: Hume and Kant","authors":["Jens Kulenkampff"],"journal":"nous","published":"1990-03-01","volume":"24","issue":"1","topics":["history"],"ha":false},{"doi":"10.2307/2108165","title":"The Primacy of Perception in Husserl's Theory of Imagining","authors":["Mark P. Drost"],"journal":"ppr","published":"1990-03-01","volume":"50","issue":"3","topics":["history","mind"],"ha":false},{"doi":"10.2307/2026632","title":"Descriptive Pronouns and Donkey Anaphora","authors":["Stephen Neale"],"journal":"jphil","published":"1990-03-01","volume":"87","issue":"3","ha":false},{"doi":"10.1093/analys/50.2.66","title":"Why supervenience?","authors":["D. Papineau"],"journal":"analysis","published":"1990-03-01","volume":"50","issue":"2","ha":false},{"doi":"10.1093/analys/50.2.80","title":"Conditionals, context, and transitivity","authors":["E. J. Lowe"],"journal":"analysis","published":"1990-03-01","volume":"50","issue":"2","ha":false},{"doi":"10.1093/analys/50.2.87","title":"Why is belief involuntary?","authors":["O. Bennett"],"journal":"analysis","published":"1990-03-01","volume":"50","issue":"2","topics":["epistemology"],"ha":false},{"doi":"10.1111/j.2041-6962.1990.tb00536.x","title":"A RESPONSE TO A. A. LONG'S “THE STOICS ON WORLD‐CONFLAGRATION AND EVERLASTING RECURRENCE”","authors":["Hud Hudson"],"journal":"sjp","published":"1990-03-01","volume":"28","issue":"1","topics":["history"],"ha":false},{"doi":"10.1111/j.2041-6962.1990.tb00567.x","title":"ON THE ORDERING OF THINGS: BEING AND POWER IN HEIDEGGER AND FOUCAULT","authors":["Hubert L. Dreyfus"],"journal":"sjp","published":"1990-03-01","volume":"28","issue":"S1","topics":["history"],"ha":false},{"doi":"10.1111/j.2041-6962.1990.tb00535.x","title":"WHY DID KANT BOTHER ABOUT ‘NOTHING’?*","authors":["Carol A. Van Kirk"],"journal":"sjp","published":"1990-03-01","volume":"28","issue":"1","topics":["history"],"ha":false},{"doi":"10.2307/2026882","title":"Personhood and Personal Identity","authors":["Marya Schechtman"],"journal":"jphil","published":"1990-02-01","volume":"87","issue":"2","topics":["metaphysics"],"ha":false},{"doi":"10.1007/bf00370973","title":"Locke on the ontology of matter, living things and persons","authors":["Vere Chappell"],"journal":"phil-studies","published":"1990-01-01","volume":"60","issue":"1-2","topics":["history","metaphysics"],"ha":false},{"doi":"10.1007/bf00370982","title":"Pyrrhonism's arguments against value","authors":["Mark L. Mcpherran"],"journal":"phil-studies","published":"1990-01-01","volume":"60","issue":"1-2","ha":false},{"doi":"10.2307/2108046","title":"Feminist Transformations of Moral Theory","authors":["Virginia Held"],"journal":"ppr","published":"1990-01-01","volume":"50","topics":["ethics","social"],"ha":false},{"doi":"10.2307/2108036","title":"Some Revisionary Proposals about Belief and Believing","authors":["Ruth Barcan Marcus"],"journal":"ppr","published":"1990-01-01","volume":"50","topics":["epistemology"],"ha":false},{"doi":"10.2307/2108038","title":"The Interpretation of Texts, People and Other Artifacts","authors":["Daniel C. Dennett"],"journal":"ppr","published":"1990-01-01","volume":"50","ha":false},{"doi":"10.1007/bf00413667","title":"Theory, intervention and realism","authors":["Margaret Morrison"],"journal":"synthese","published":"1990-01-01","volume":"82","issue":"1","topics":["metaphysics","philsci"],"ha":false},{"doi":"10.1093/mind/xcix.394.185","title":"There is No Question of Physicalism","authors":["TIM CRANE","D. H. MELLOR"],"journal":"mind","published":"1990-01-01","volume":"XCIX","issue":"394","ha":false},{"doi":"10.1093/mind/xcix.394.157","title":"Varieties of Pragmatism","authors":["ROBERT KRAUT"],"journal":"mind","published":"1990-01-01","volume":"XCIX","issue":"394","ha":false},{"doi":"10.1093/mind/xcix.393.53","title":"Subcognition and the Limits of the TuringTest","authors":["ROBERT M. FRENCH"],"journal":"mind","published":"1990-01-01","volume":"XCIX","issue":"393","topics":["mind"],"ha":false},{"doi":"10.1093/mind/xcix.395.327","title":"Modal Fictionalism","authors":["GIDEON ROSEN"],"journal":"mind","published":"1990-01-01","volume":"XCIX","issue":"395","topics":["aesthetics"],"ha":false},{"doi":"10.1093/mind/xcix.393.24","title":"Noneism or Allism?","authors":["DAVID LEWIS"],"journal":"mind","published":"1990-01-01","volume":"XCIX","issue":"393","ha":false},{"doi":"10.1093/mind/xcix.393.1","title":"The Reality of Rule-Following","authors":["PHILIP PETTIT"],"journal":"mind","published":"1990-01-01","volume":"XCIX","issue":"393","ha":false},{"doi":"10.1093/mind/xcix.396.501","title":"Brouwerian Intuitionism","authors":["MICHAEL DETLEFSEN"],"journal":"mind","published":"1990-01-01","volume":"XCIX","issue":"396","ha":false},{"doi":"10.1093/mind/xcix.396.583","title":"Is a Whole Identical to its Parts?","authors":["THEODORE SCALTSAS"],"journal":"mind","published":"1990-01-01","volume":"XCIX","issue":"396","ha":false},{"doi":"10.1093/mind/xcix.394.267","title":"How ‘Russellian’ Was Frege?","authors":["DAVID BELL"],"journal":"mind","published":"1990-01-01","volume":"XCIX","issue":"394","topics":["history"],"ha":false},{"doi":"10.2307/2185202","title":"The Priority of Reason in Descartes","authors":["Louis E. Loeb"],"journal":"phil-review","published":"1990-01-01","volume":"99","issue":"1","topics":["history"],"ha":false},{"doi":"10.2307/2185215","title":"The Intentional Stance.","authors":["Patricia Kitcher","Daniel C. Dennett"],"journal":"phil-review","published":"1990-01-01","volume":"99","issue":"1","topics":["action"],"ha":false},{"doi":"10.2307/2185217","title":"The Theory of Epistemic Rationality.","authors":["Hilary Kornblith","Richard Foley"],"journal":"phil-review","published":"1990-01-01","volume":"99","issue":"1","topics":["epistemology"],"ha":false},{"doi":"10.2307/2026863","title":"The Structure and Content of Truth","authors":["Donald Davidson","Journal of Philosophy Inc."],"journal":"jphil","published":"1990-01-01","volume":"87","issue":"6","ha":false},{"doi":"10.2307/2026969","title":"Troubles with Ockhamism","authors":["David Widerker","Journal of Philosophy Inc."],"journal":"jphil","published":"1990-01-01","volume":"87","issue":"9","ha":false},{"doi":"10.5840/jphil1990871123","title":"Cartesian Skepticism and Inference to the Best Explanation","authors":["Jonathan Vogel","Journal of Philosophy Inc."],"journal":"jphil","published":"1990-01-01","volume":"87","issue":"11","topics":["epistemology","history","logic","philsci"],"ha":false},{"doi":"10.5840/jphil1990871026","title":"\"But Would That Still Be Me?\" Notes on Gender, \"Race,\" Ethnicity, as Sources of \"Identity\"","authors":["Anthony Appiah","Journal of Philosophy Inc."],"journal":"jphil","published":"1990-01-01","volume":"87","issue":"10","topics":["social"],"ha":false},{"doi":"10.2307/2026968","title":"National Self-determination","authors":["Avishai Margalit","Joseph Raz","Journal of Philosophy Inc."],"journal":"jphil","published":"1990-01-01","volume":"87","issue":"9","ha":false},{"doi":"10.2307/2026796","title":"The Division of Cognitive Labor","authors":["Philip Kitcher"],"journal":"jphil","published":"1990-01-01","volume":"87","issue":"1","topics":["mind"],"ha":false},{"doi":"10.1093/analys/50.1.42","title":"Is the best really necessary?","authors":["E. R. Kraemer"],"journal":"analysis","published":"1990-01-01","volume":"50","issue":"1","ha":false},{"doi":"10.1093/analys/50.1.36","title":"Paternalism defined","authors":["D. Archard"],"journal":"analysis","published":"1990-01-01","volume":"50","issue":"1","ha":false},{"doi":"10.1111/j.1467-9973.1990.tb00830.x","title":"SUPERVENIENCE AS A PHILOSOPHICAL CONCEPT*","authors":["JAEGWON KIM"],"journal":"metaphilosophy","published":"1990-01-01","volume":"21","issue":"1-2","ha":false},{"doi":"10.1111/j.1467-9973.1990.tb00832.x","title":"THE RHETORIC OF GRAMMAR: UNDERSTANDING WITTGENSTEIN'S METHOD","authors":["WILLIAM E. BARNETT"],"journal":"metaphilosophy","published":"1990-01-01","volume":"21","issue":"1-2","topics":["epistemology","history"],"ha":false},{"doi":"10.1017/s0031819100064263","title":"The Nature of Artifacts","authors":["Michael Losonsky"],"journal":"philosophy","published":"1990-01-01","volume":"65","issue":"251","topics":["history","metaphysics"],"ha":true},{"doi":"10.5840/ipq199030436","title":"Mystical Experience, Hermeneutics, and Rationality","authors":["Jonathan Shear"],"journal":"ipq","published":"1990-01-01","volume":"30","issue":"4","topics":["epistemology"],"ha":false},{"doi":"10.2307/2214188","title":"Phenomenal States","authors":["Brian Loar"],"journal":"phil-perspectives","published":"1990-01-01","volume":"4","topics":["mind"],"ha":false},{"doi":"10.2307/2214186","title":"The Intrinsic Quality of Experience","authors":["Gilbert Harman"],"journal":"phil-perspectives","published":"1990-01-01","volume":"4","ha":false},{"doi":"10.2307/2214205","title":"Understanding and the Principle of Compositionality","authors":["Richard E. Grandy"],"journal":"phil-perspectives","published":"1990-01-01","volume":"4","topics":["epistemology","metaphysics"],"ha":false},{"doi":"10.2307/2214202","title":"Connectionism, Eliminativism and The Future of Folk Psychology","authors":["William Ramsey","Stephen Stich","Joseph Garon"],"journal":"phil-perspectives","published":"1990-01-01","volume":"4","ha":false},{"doi":"10.2307/2214187","title":"Inverted Earth","authors":["Ned Block"],"journal":"phil-perspectives","published":"1990-01-01","volume":"4","ha":false},{"doi":"10.2307/2214191","title":"Physicalism","authors":["Stephen Schiffer"],"journal":"phil-perspectives","published":"1990-01-01","volume":"4","ha":false},{"doi":"10.2307/2214189","title":"What is the \"Subjectivity\" of the Mental","authors":["William G. Lycan"],"journal":"phil-perspectives","published":"1990-01-01","volume":"4","topics":["mind"],"ha":false},{"doi":"10.5840/monist199073116","title":"Epicurus on Pleasure and the Complete Life","authors":["Stephen E. Rosenbaum","The Hegeler Institute"],"journal":"monist","published":"1990-01-01","volume":"73","issue":"1","ha":false},{"doi":"10.5840/monist199073119","title":"The Hellenistic Version of Aristotle’s Ethics","authors":["Julia Annas","The Hegeler Institute"],"journal":"monist","published":"1990-01-01","volume":"73","issue":"1","topics":["ethics","history"],"ha":false},{"doi":"10.5840/monist199073225","title":"Beneath Interpretation: Against Hermeneutic Holism","authors":["Richard Shusterman","The Hegeler Institute"],"journal":"monist","published":"1990-01-01","volume":"73","issue":"2","ha":false},{"doi":"10.5840/philtopics19901824","title":"The Bohr Atom, Models, and Realism","authors":["R. I. G. Hughes","University of Arkansas Press"],"journal":"phil-topics","published":"1990-01-01","volume":"18","issue":"2","topics":["metaphysics","philsci"],"ha":false},{"doi":"10.1086/293181","title":"Rights, Justice, and Duties to Provde Assistance: A Critique of Regan's Theory of Rights","authors":["Dale Jamieson"],"journal":"ethics","published":"1990-01-01","volume":"100","issue":"2","topics":["ethics","political"],"ha":false},{"doi":"10.1086/293179","title":"Paternalism and Respect for Autonomy","authors":["Danny Scoccia"],"journal":"ethics","published":"1990-01-01","volume":"100","issue":"2","topics":["ethics"],"ha":false},{"doi":"10.1086/293185","title":"Sex and Power Feminism Unmodified: Discourses on Life and Law . Catherine A. MacKinnon","authors":["Carole Pateman"],"journal":"ethics","published":"1990-01-01","volume":"100","issue":"2","topics":["ethics","social"],"ha":false},{"doi":"10.1007/bf02423832","title":"Species of thought: A comment on evolutionary epistemology","authors":["David Sloan Wilson"],"journal":"bio-phil","published":"1990-01-01","volume":"5","issue":"1","topics":["epistemology","philsci"],"ha":false}]