[{"doi":"10.1215/00318108-111-4-605","title":"Complex Demonstratives: A Quantificational Account","authors":["Jason Stanley"],"journal":"phil-review","published":"2002-10-01","volume":"111","issue":"4","pages":"605-609","abstract":"","topics":["logic"],"si":null,"url":"https://doi.org/10.1215/00318108-111-4-605"},{"doi":"10.2307/1556429","title":"Post-Hellenistic Philosophy: A Study of Its Development from the Stoics to Origen","authors":["R. W. Sharples","G. R. Boys-Stones"],"journal":"phil-review","published":"2002-10-01","volume":"111","issue":"4","pages":"573","abstract":"","topics":["history"],"si":null,"url":"https://doi.org/10.2307/1556429"},{"doi":"10.2307/1556434","title":"Scientific Essentialism","authors":["Lenny Clapp","Brian Ellis"],"journal":"phil-review","published":"2002-10-01","volume":"111","issue":"4","pages":"589","abstract":"","topics":["philsci"],"si":null,"url":"https://doi.org/10.2307/1556434"},{"doi":"10.1215/00318108-111-4-576","title":"The Cambridge Translations of Medieval Philosophical Texts , vol. 2: Ethics and Political Philosophy","authors":["Thomas Williams"],"journal":"phil-review","published":"2002-10-01","volume":"111","issue":"4","pages":"576-578","abstract":"","topics":["ethics","history","political"],"si":null,"url":"https://doi.org/10.1215/00318108-111-4-576"},{"doi":"10.1215/00318108-111-4-573","title":"Post-Hellenistic Philosophy: A Study of Its Development from the Stoics to Origen","authors":["R.W. Sharples"],"journal":"phil-review","published":"2002-10-01","volume":"111","issue":"4","pages":"573-575","abstract":"","topics":["history"],"si":null,"url":"https://doi.org/10.1215/00318108-111-4-573"},{"doi":"10.1215/00318108-111-4-586","title":"Objects and Persons","authors":["Michael B. Burke"],"journal":"phil-review","published":"2002-10-01","volume":"111","issue":"4","pages":"586-588","abstract":"","topics":[],"si":null,"url":"https://doi.org/10.1215/00318108-111-4-586"},{"doi":"10.1215/00318108-111-4-616","title":"Morals from Motives","authors":["Kieran Setiya"],"journal":"phil-review","published":"2002-10-01","volume":"111","issue":"4","pages":"616-618","abstract":"","topics":["ethics"],"si":null,"url":"https://doi.org/10.1215/00318108-111-4-616"},{"doi":"10.1215/00318108-111-4-539","title":"Maxims and Virtues","authors":["Talbot Brewer"],"journal":"phil-review","published":"2002-10-01","volume":"111","issue":"4","pages":"539-572","abstract":"","topics":["ethics"],"si":null,"url":"https://doi.org/10.1215/00318108-111-4-539"},{"doi":"10.1215/00318108-111-4-594","title":"Purple Haze: The Puzzle of Consciousness","authors":["Alex Byrne"],"journal":"phil-review","published":"2002-10-01","volume":"111","issue":"4","pages":"594-597","abstract":"","topics":["mind"],"si":null,"url":"https://doi.org/10.1215/00318108-111-4-594"},{"doi":"10.1215/00318108-111-4-579","title":"Poincaré's Philosophy: From Conventionalism to Phenomenology","authors":["Emily Carson"],"journal":"phil-review","published":"2002-10-01","volume":"111","issue":"4","pages":"579-582","abstract":"","topics":[],"si":null,"url":"https://doi.org/10.1215/00318108-111-4-579"},{"doi":"10.1215/00318108-111-4-618","title":"Justice as Fairness: A Restatement","authors":["Thaddeus Metz"],"journal":"phil-review","published":"2002-10-01","volume":"111","issue":"4","pages":"618-620","abstract":"","topics":["political"],"si":null,"url":"https://doi.org/10.1215/00318108-111-4-618"},{"doi":"10.2307/1556441","title":"Morals from Motives","authors":["Kieran Setiya","Michael Slote"],"journal":"phil-review","published":"2002-10-01","volume":"111","issue":"4","pages":"616","abstract":"","topics":["ethics"],"si":null,"url":"https://doi.org/10.2307/1556441"},{"doi":"10.2307/1556436","title":"Knowledge, Possibility, and Consciousness","authors":["Jessica Wilson","John Perry"],"journal":"phil-review","published":"2002-10-01","volume":"111","issue":"4","pages":"598","abstract":"","topics":["epistemology","mind"],"si":null,"url":"https://doi.org/10.2307/1556436"},{"doi":"10.1215/00318108-111-4-598","title":"Knowledge, Possibility, and Consciousness","authors":["Jessica Wilson"],"journal":"phil-review","published":"2002-10-01","volume":"111","issue":"4","pages":"598-602","abstract":"","topics":["epistemology","mind"],"si":null,"url":"https://doi.org/10.1215/00318108-111-4-598"},{"doi":"10.2307/1556427","title":"Demonstrating and Necessity","authors":["Nathan Salmon"],"journal":"phil-review","published":"2002-10-01","volume":"111","issue":"4","pages":"497","abstract":"","topics":[],"si":null,"url":"https://doi.org/10.2307/1556427"},{"doi":"10.1215/00318108-111-4-602","title":"Truth and the Absence of Fact","authors":["John P. Burgess"],"journal":"phil-review","published":"2002-10-01","volume":"111","issue":"4","pages":"602-604","abstract":"","topics":[],"si":null,"url":"https://doi.org/10.1215/00318108-111-4-602"},{"doi":"10.1215/00318108-111-4-609","title":"Real Conditionals","authors":["Brian Weatherson"],"journal":"phil-review","published":"2002-10-01","volume":"111","issue":"4","pages":"609-611","abstract":"","topics":[],"si":null,"url":"https://doi.org/10.1215/00318108-111-4-609"},{"doi":"10.2307/1556431","title":"Poincaré's Philosophy: From Conventionalism to Phenomenology","authors":["Emily Carson","Elie Zahar"],"journal":"phil-review","published":"2002-10-01","volume":"111","issue":"4","pages":"579","abstract":"","topics":[],"si":null,"url":"https://doi.org/10.2307/1556431"},{"doi":"10.2307/1556435","title":"Purple Haze: The Puzzle of Consciousness","authors":["Alex Byrne","Joseph Levine"],"journal":"phil-review","published":"2002-10-01","volume":"111","issue":"4","pages":"594","abstract":"","topics":["mind"],"si":null,"url":"https://doi.org/10.2307/1556435"},{"doi":"10.2307/1556430","title":"The Cambridge Translations of Medieval Philosophical Texts, Vol. 2: Ethics and Political Philosophy","authors":["Thomas Williams","Arthur Stephen McGrade","John Kilcullen","Matthew Kempshall"],"journal":"phil-review","published":"2002-10-01","volume":"111","issue":"4","pages":"576","abstract":"","topics":["ethics","history","political"],"si":null,"url":"https://doi.org/10.2307/1556430"},{"doi":"10.2307/1556443","title":"War Crimes and Collective Wrongdoing: A Reader","authors":["David Luban","Aleksandar Jokic"],"journal":"phil-review","published":"2002-10-01","volume":"111","issue":"4","pages":"620","abstract":"","topics":["ethics","social"],"si":null,"url":"https://doi.org/10.2307/1556443"},{"doi":"10.2307/1556433","title":"Objects and Persons","authors":["Michael B. Burke","Trenton Merricks"],"journal":"phil-review","published":"2002-10-01","volume":"111","issue":"4","pages":"586","abstract":"","topics":[],"si":null,"url":"https://doi.org/10.2307/1556433"},{"doi":"10.2307/1556432","title":"Signs of Sense: Reading Wittgenstein's Tractatus","authors":["Edward Minar","Eli Friedlander"],"journal":"phil-review","published":"2002-10-01","volume":"111","issue":"4","pages":"583","abstract":"","topics":["history"],"si":null,"url":"https://doi.org/10.2307/1556432"},{"doi":"10.1215/00318108-111-4-583","title":"Signs of Sense: Reading Wittgenstein's Tractatus","authors":["Edward Minar"],"journal":"phil-review","published":"2002-10-01","volume":"111","issue":"4","pages":"583-585","abstract":"","topics":["history"],"si":null,"url":"https://doi.org/10.1215/00318108-111-4-583"},{"doi":"10.2307/1556439","title":"Real Conditionals","authors":["Brian Weatherson","William G. Lycan"],"journal":"phil-review","published":"2002-10-01","volume":"111","issue":"4","pages":"609","abstract":"","topics":[],"si":null,"url":"https://doi.org/10.2307/1556439"},{"doi":"10.1215/00318108-111-4-612","title":"Autonomous Agents: From Self-Control to Autonomy","authors":["Michael McKenna"],"journal":"phil-review","published":"2002-10-01","volume":"111","issue":"4","pages":"612-615","abstract":"","topics":[],"si":null,"url":"https://doi.org/10.1215/00318108-111-4-612"},{"doi":"10.2307/1556442","title":"Justice as Fairness: A Restatement","authors":["Thaddeus Metz","John Rawls","Erin Kelly"],"journal":"phil-review","published":"2002-10-01","volume":"111","issue":"4","pages":"618","abstract":"","topics":["political"],"si":null,"url":"https://doi.org/10.2307/1556442"},{"doi":"10.2307/1556428","title":"Maxims and Virtues","authors":["Talbot Brewer"],"journal":"phil-review","published":"2002-10-01","volume":"111","issue":"4","pages":"539","abstract":"","topics":["ethics"],"si":null,"url":"https://doi.org/10.2307/1556428"},{"doi":"10.1215/00318108-111-4-589","title":"Scientific Essentialism","authors":["Lenny Clapp"],"journal":"phil-review","published":"2002-10-01","volume":"111","issue":"4","pages":"589-594","abstract":"","topics":["philsci"],"si":null,"url":"https://doi.org/10.1215/00318108-111-4-589"},{"doi":"10.2307/1556440","title":"Autonomous Agents: From Self-Control to Autonomy","authors":["Michael McKenna","Alfred R. Mele"],"journal":"phil-review","published":"2002-10-01","volume":"111","issue":"4","pages":"612","abstract":"","topics":[],"si":null,"url":"https://doi.org/10.2307/1556440"},{"doi":"10.1215/00318108-111-4-620","title":"War Crimes and Collective Wrongdoing: A Reader","authors":["David Luban"],"journal":"phil-review","published":"2002-10-01","volume":"111","issue":"4","pages":"620-624","abstract":"","topics":["ethics","social"],"si":null,"url":"https://doi.org/10.1215/00318108-111-4-620"},{"doi":"10.2307/1556437","title":"Truth and the Absence of Fact","authors":["John P. Burgess","Hartry Field"],"journal":"phil-review","published":"2002-10-01","volume":"111","issue":"4","pages":"602","abstract":"","topics":[],"si":null,"url":"https://doi.org/10.2307/1556437"},{"doi":"10.2307/1556438","title":"Complex Demonstratives: A Quantificational Account","authors":["Jason Stanley","Jeffrey C. King"],"journal":"phil-review","published":"2002-10-01","volume":"111","issue":"4","pages":"605","abstract":"","topics":["logic"],"si":null,"url":"https://doi.org/10.2307/1556438"},{"doi":"10.1215/00318108-111-4-497","title":"Demonstrating and Necessity","authors":["Nathan Salmon"],"journal":"phil-review","published":"2002-10-01","volume":"111","issue":"4","pages":"497-537","abstract":"","topics":[],"si":null,"url":"https://doi.org/10.1215/00318108-111-4-497"},{"doi":"10.1215/00318108-111-3-442","title":"Reason's Nearest Kin","authors":["Sanford Shieh"],"journal":"phil-review","published":"2002-07-01","volume":"111","issue":"3","pages":"442-447","abstract":"","topics":[],"si":null,"url":"https://doi.org/10.1215/00318108-111-3-442"},{"doi":"10.2307/3182563","title":"Moral Particularism","authors":["Pekka Vayrynen","Brad Hooker","Margaret Little"],"journal":"phil-review","published":"2002-07-01","volume":"111","issue":"3","pages":"478","abstract":"","topics":["ethics"],"si":null,"url":"https://doi.org/10.2307/3182563"},{"doi":"10.1215/00318108-111-3-456","title":"The Soul","authors":["Christina Van Dyke"],"journal":"phil-review","published":"2002-07-01","volume":"111","issue":"3","pages":"456-458","abstract":"","topics":["religion"],"si":null,"url":"https://doi.org/10.1215/00318108-111-3-456"},{"doi":"10.1215/00318108-111-3-478","title":"Moral Particularism","authors":["Pekka Väyrynen"],"journal":"phil-review","published":"2002-07-01","volume":"111","issue":"3","pages":"478-483","abstract":"","topics":["ethics"],"si":null,"url":"https://doi.org/10.1215/00318108-111-3-478"},{"doi":"10.2307/3182549","title":"Reflections on Knowledge and Its Limits","authors":["Gilbert Harman"],"journal":"phil-review","published":"2002-07-01","volume":"111","issue":"3","pages":"417","abstract":"","topics":["epistemology"],"si":null,"url":"https://doi.org/10.2307/3182549"},{"doi":"10.1215/00318108-111-3-373","title":"Thomas Reid's Geometry of Visibles","authors":["James Van Cleve"],"journal":"phil-review","published":"2002-07-01","volume":"111","issue":"3","pages":"373-416","abstract":"","topics":[],"si":null,"url":"https://doi.org/10.1215/00318108-111-3-373"},{"doi":"10.2307/3182553","title":"Reason's Nearest Kin","authors":["Sanford Shieh","Michael Potter"],"journal":"phil-review","published":"2002-07-01","volume":"111","issue":"3","pages":"442","abstract":"","topics":[],"si":null,"url":"https://doi.org/10.2307/3182553"},{"doi":"10.1215/00318108-111-3-483","title":"Complicity: Ethics and Law for a Collective Age","authors":["Larry May"],"journal":"phil-review","published":"2002-07-01","volume":"111","issue":"3","pages":"483-486","abstract":"","topics":["ethics","social"],"si":null,"url":"https://doi.org/10.1215/00318108-111-3-483"},{"doi":"10.2307/3182554","title":"Cassirer's \"Metaphysics of Symbolic Forms\"","authors":["Charlie Huenemann","Thora Ilin Bayer"],"journal":"phil-review","published":"2002-07-01","volume":"111","issue":"3","pages":"447","abstract":"","topics":["metaphysics","philsci"],"si":null,"url":"https://doi.org/10.2307/3182554"},{"doi":"10.2307/3182557","title":"The Soul","authors":["Christina Van Dyke","William of Auvergne","Roland Teske"],"journal":"phil-review","published":"2002-07-01","volume":"111","issue":"3","pages":"456","abstract":"","topics":["religion"],"si":null,"url":"https://doi.org/10.2307/3182557"},{"doi":"10.1215/00318108-111-3-449","title":"Heidegger's Concept of Truth","authors":["Edward Witherspoon"],"journal":"phil-review","published":"2002-07-01","volume":"111","issue":"3","pages":"449-452","abstract":"","topics":["history"],"si":null,"url":"https://doi.org/10.1215/00318108-111-3-449"},{"doi":"10.1215/00318108-111-3-429","title":"Critique of the Power of Judgment","authors":["Hannah Ginsborg"],"journal":"phil-review","published":"2002-07-01","volume":"111","issue":"3","pages":"429-435","abstract":"","topics":[],"si":null,"url":"https://doi.org/10.1215/00318108-111-3-429"},{"doi":"10.2307/3182551","title":"Kant and Modern Political Philosophy","authors":["Samuel J. Kerstein","Katrin Flikschuh"],"journal":"phil-review","published":"2002-07-01","volume":"111","issue":"3","pages":"436","abstract":"","topics":["history","political"],"si":null,"url":"https://doi.org/10.2307/3182551"},{"doi":"10.2307/3182550","title":"Critique of the Power of Judgment","authors":["Hannah Ginsborg","Immanuel Kant","Paul Guyer","Eric Matthews"],"journal":"phil-review","published":"2002-07-01","volume":"111","issue":"3","pages":"429","abstract":"","topics":[],"si":null,"url":"https://doi.org/10.2307/3182550"},{"doi":"10.2307/3182559","title":"Logical Properties: Identity, Existence, Predication, Necessity, Truth","authors":["John MacFarlane","Colin McGinn"],"journal":"phil-review","published":"2002-07-01","volume":"111","issue":"3","pages":"462","abstract":"","topics":["language","logic"],"si":null,"url":"https://doi.org/10.2307/3182559"},{"doi":"10.2307/3182548","title":"Thomas Reid's Geometry of Visibles","authors":["James Van Cleve"],"journal":"phil-review","published":"2002-07-01","volume":"111","issue":"3","pages":"373","abstract":"","topics":[],"si":null,"url":"https://doi.org/10.2307/3182548"},{"doi":"10.2307/3182558","title":"Oratio Obliqua, Oratio Recta: An Essay on Metarepresentation","authors":["Tomis Kapitan","Francois Recanati"],"journal":"phil-review","published":"2002-07-01","volume":"111","issue":"3","pages":"459","abstract":"","topics":["mind"],"si":null,"url":"https://doi.org/10.2307/3182558"},{"doi":"10.1215/00318108-111-3-447","title":"Cassirer's Metaphysics of Symbolic Forms","authors":["Charlie Huenemann"],"journal":"phil-review","published":"2002-07-01","volume":"111","issue":"3","pages":"447-449","abstract":"","topics":["metaphysics","philsci"],"si":null,"url":"https://doi.org/10.1215/00318108-111-3-447"},{"doi":"10.1215/00318108-111-3-436","title":"Kant and Modern Political Philosophy","authors":["Samuel J. Kerstein"],"journal":"phil-review","published":"2002-07-01","volume":"111","issue":"3","pages":"436-439","abstract":"","topics":["history","political"],"si":null,"url":"https://doi.org/10.1215/00318108-111-3-436"},{"doi":"10.2307/3182552","title":"Substance, Force, and the Possibility of Knowledge: On Kant's Philosophy of Nature","authors":["Alison Laywine","Jeffrey Edwards"],"journal":"phil-review","published":"2002-07-01","volume":"111","issue":"3","pages":"439","abstract":"","topics":["epistemology","history"],"si":null,"url":"https://doi.org/10.2307/3182552"},{"doi":"10.2307/3182561","title":"Unshadowed Thought: Representations in Thought and Language","authors":["Reinaldo Elugardo","Robert J. Stainton","Charles Travis"],"journal":"phil-review","published":"2002-07-01","volume":"111","issue":"3","pages":"470","abstract":"","topics":["language","mind"],"si":null,"url":"https://doi.org/10.2307/3182561"},{"doi":"10.2307/3182555","title":"Heidegger's Concept of Truth","authors":["Edward Witherspoon","Daniel O. Dahlstrom"],"journal":"phil-review","published":"2002-07-01","volume":"111","issue":"3","pages":"449","abstract":"","topics":["history"],"si":null,"url":"https://doi.org/10.2307/3182555"},{"doi":"10.2307/3182560","title":"Circularity, Definition and Truth","authors":["Michael Glanzberg","Andre Chapuis","Anil Gupta"],"journal":"phil-review","published":"2002-07-01","volume":"111","issue":"3","pages":"465","abstract":"","topics":[],"si":null,"url":"https://doi.org/10.2307/3182560"},{"doi":"10.1215/00318108-111-3-459","title":"Oratio Obliqua, Oratio Recta: An Essay on Metarepresentation","authors":["Tomis Kapitan"],"journal":"phil-review","published":"2002-07-01","volume":"111","issue":"3","pages":"459-462","abstract":"","topics":["mind"],"si":null,"url":"https://doi.org/10.1215/00318108-111-3-459"},{"doi":"10.1215/00318108-111-3-452","title":"Substantial Knowledge: Aristotle's Metaphysics","authors":["S. Marc Cohen"],"journal":"phil-review","published":"2002-07-01","volume":"111","issue":"3","pages":"452-456","abstract":"","topics":["epistemology","history","metaphysics","philsci"],"si":null,"url":"https://doi.org/10.1215/00318108-111-3-452"},{"doi":"10.1215/00318108-111-3-462","title":"Logical Properties: Identity, Existence, Predication, Necessity, Truth","authors":["John MacFarlane"],"journal":"phil-review","published":"2002-07-01","volume":"111","issue":"3","pages":"462-465","abstract":"","topics":["language","logic"],"si":null,"url":"https://doi.org/10.1215/00318108-111-3-462"},{"doi":"10.1215/00318108-111-3-341","title":"Designating Propositions","authors":["Jeffrey C. King"],"journal":"phil-review","published":"2002-07-01","volume":"111","issue":"3","pages":"341-371","abstract":"","topics":["language"],"si":null,"url":"https://doi.org/10.1215/00318108-111-3-341"},{"doi":"10.1215/00318108-111-3-470","title":"Unshadowed Thought: Representations in Thought and Language","authors":["Reinaldo Elugardo","Robert J. Stainton"],"journal":"phil-review","published":"2002-07-01","volume":"111","issue":"3","pages":"470-473","abstract":"","topics":["language","mind"],"si":null,"url":"https://doi.org/10.1215/00318108-111-3-470"},{"doi":"10.2307/3182547","title":"Designating Propositions","authors":["Jeffrey C. King"],"journal":"phil-review","published":"2002-07-01","volume":"111","issue":"3","pages":"341","abstract":"","topics":["language"],"si":null,"url":"https://doi.org/10.2307/3182547"},{"doi":"10.2307/3182562","title":"Metaphor in Context","authors":["David Hills","Josef Stern"],"journal":"phil-review","published":"2002-07-01","volume":"111","issue":"3","pages":"473","abstract":"","topics":["language"],"si":null,"url":"https://doi.org/10.2307/3182562"},{"doi":"10.1215/00318108-111-3-417","title":"Reflections on Knowledge and its Limits","authors":["Gilbert Harman"],"journal":"phil-review","published":"2002-07-01","volume":"111","issue":"3","pages":"417-428","abstract":"","topics":["epistemology"],"si":null,"url":"https://doi.org/10.1215/00318108-111-3-417"},{"doi":"10.1215/00318108-111-3-439","title":"Substance, Force, and the Possibility of Knowledge: On Kant's Philosophy of Nature","authors":["Alison Laywine"],"journal":"phil-review","published":"2002-07-01","volume":"111","issue":"3","pages":"439-442","abstract":"","topics":["epistemology","history"],"si":null,"url":"https://doi.org/10.1215/00318108-111-3-439"},{"doi":"10.2307/3182556","title":"Substantial Knowledge: Aristotle's Metaphysics","authors":["S. Marc Cohen","C. D. C. Reeve"],"journal":"phil-review","published":"2002-07-01","volume":"111","issue":"3","pages":"452","abstract":"","topics":["epistemology","history","metaphysics","philsci"],"si":null,"url":"https://doi.org/10.2307/3182556"},{"doi":"10.1215/00318108-111-3-465","title":"Circularity, Definition and Truth","authors":["Michael Glanzberg"],"journal":"phil-review","published":"2002-07-01","volume":"111","issue":"3","pages":"465-470","abstract":"","topics":[],"si":null,"url":"https://doi.org/10.1215/00318108-111-3-465"},{"doi":"10.1215/00318108-111-3-473","title":"Metaphor in Context","authors":["David Hills"],"journal":"phil-review","published":"2002-07-01","volume":"111","issue":"3","pages":"473-478","abstract":"","topics":["language"],"si":null,"url":"https://doi.org/10.1215/00318108-111-3-473"},{"doi":"10.2307/3182564","title":"Complicity: Ethics and Law for a Collective Age","authors":["Larry May","Christopher Kutz"],"journal":"phil-review","published":"2002-07-01","volume":"111","issue":"3","pages":"483","abstract":"","topics":["ethics","social"],"si":null,"url":"https://doi.org/10.2307/3182564"},{"doi":"10.1215/00318108-111-2-270","title":"Philosophical and Ethical Problems in Mental Handicap","authors":["Agnieszka Jaworska"],"journal":"phil-review","published":"2002-04-01","volume":"111","issue":"2","pages":"270-275","abstract":"","topics":["ethics","mind"],"si":null,"url":"https://doi.org/10.1215/00318108-111-2-270"},{"doi":"10.1215/00318108-111-2-235","title":"Reply to Huemer on the Consequence Argument","authors":["Helen Beebee"],"journal":"phil-review","published":"2002-04-01","volume":"111","issue":"2","pages":"235-241","abstract":"","topics":[],"si":null,"url":"https://doi.org/10.1215/00318108-111-2-235"},{"doi":"10.2307/3182639","title":"The Cambridge Companion to German Idealism","authors":["Klaus Brinkmann","Karl Ameriks"],"journal":"phil-review","published":"2002-04-01","volume":"111","issue":"2","pages":"318","abstract":"","topics":[],"si":null,"url":"https://doi.org/10.2307/3182639"},{"doi":"10.2307/3182623","title":"Sex and Social Justice","authors":["Rachana Kamtekar","Martha Nussbaum"],"journal":"phil-review","published":"2002-04-01","volume":"111","issue":"2","pages":"262","abstract":"","topics":["political"],"si":null,"url":"https://doi.org/10.2307/3182623"},{"doi":"10.1215/00318108-111-2-259","title":"Finite and Infinite Goods: A Framework for Ethics","authors":["Melissa Barry"],"journal":"phil-review","published":"2002-04-01","volume":"111","issue":"2","pages":"259-261","abstract":"","topics":["ethics"],"si":null,"url":"https://doi.org/10.1215/00318108-111-2-259"},{"doi":"10.1215/00318108-111-2-314","title":"Berkeley's Thought","authors":["Lex Newman"],"journal":"phil-review","published":"2002-04-01","volume":"111","issue":"2","pages":"314-318","abstract":"","topics":["history"],"si":null,"url":"https://doi.org/10.1215/00318108-111-2-314"},{"doi":"10.1215/00318108-111-2-297","title":"Platonic Questions: Dialogues with the Silent Philosopher","authors":["Chris Bobonich"],"journal":"phil-review","published":"2002-04-01","volume":"111","issue":"2","pages":"297-299","abstract":"","topics":["history"],"si":null,"url":"https://doi.org/10.1215/00318108-111-2-297"},{"doi":"10.2307/3182621","title":"The Formal-Structural View of Logical Consequence: A Reply to Gila Sher","authors":["William H. Hanson"],"journal":"phil-review","published":"2002-04-01","volume":"111","issue":"2","pages":"243","abstract":"","topics":["logic"],"si":null,"url":"https://doi.org/10.2307/3182621"},{"doi":"10.1215/00318108-111-2-167","title":"Assertion, Knowledge, and Context","authors":["Keith DeRose"],"journal":"phil-review","published":"2002-04-01","volume":"111","issue":"2","pages":"167-203","abstract":"","topics":["epistemology","language"],"si":null,"url":"https://doi.org/10.1215/00318108-111-2-167"},{"doi":"10.1215/00318108-111-2-262","title":"Sex and Social Justice; Women and Human Development: The Capabilities Approach","authors":["Rachana Kamtekar"],"journal":"phil-review","published":"2002-04-01","volume":"111","issue":"2","pages":"262-270","abstract":"","topics":["political"],"si":null,"url":"https://doi.org/10.1215/00318108-111-2-262"},{"doi":"10.2307/3182633","title":"Plato and His Predecessors: The Dramatisation of Reason","authors":["John Palmer","Mary Margaret McCabe"],"journal":"phil-review","published":"2002-04-01","volume":"111","issue":"2","pages":"299","abstract":"","topics":["history"],"si":null,"url":"https://doi.org/10.2307/3182633"},{"doi":"10.2307/3182624","title":"Philosophical and Ethical Problems in Mental Handicap","authors":["Agnieszka Jaworska","Peter Byrne"],"journal":"phil-review","published":"2002-04-01","volume":"111","issue":"2","pages":"270","abstract":"","topics":["ethics","mind"],"si":null,"url":"https://doi.org/10.2307/3182624"},{"doi":"10.2307/3182622","title":"Finite and Infinite Goods: A Framework for Ethics","authors":["Melissa Barry","Robert Adams"],"journal":"phil-review","published":"2002-04-01","volume":"111","issue":"2","pages":"259","abstract":"","topics":["ethics"],"si":null,"url":"https://doi.org/10.2307/3182622"},{"doi":"10.1215/00318108-111-2-284","title":"Articulating Reasons: An Introduction to Inferentialism","authors":["Steven Gross"],"journal":"phil-review","published":"2002-04-01","volume":"111","issue":"2","pages":"284-287","abstract":"","topics":[],"si":null,"url":"https://doi.org/10.1215/00318108-111-2-284"},{"doi":"10.2307/3182628","title":"Articulating Reasons: An Introduction to Inferentialism","authors":["Steven Gross","Robert B. Brandom"],"journal":"phil-review","published":"2002-04-01","volume":"111","issue":"2","pages":"284","abstract":"","topics":[],"si":null,"url":"https://doi.org/10.2307/3182628"},{"doi":"10.2307/3182631","title":"Cause and Explanation in Ancient Greek Thought","authors":["Michael Ferejohn","R. J. Hankinson"],"journal":"phil-review","published":"2002-04-01","volume":"111","issue":"2","pages":"294","abstract":"","topics":["history","philsci"],"si":null,"url":"https://doi.org/10.2307/3182631"},{"doi":"10.2307/3182627","title":"Knowledge, Mind, and the Given: Reading Wilfrid Sellars's \"Empiricism and the Philosophy of Mind,\" including the Complete Text of Sellars's Essay","authors":["Danielle Macbeth","Wilfrid Sellars","Willem A. deVries","Timm Triplett"],"journal":"phil-review","published":"2002-04-01","volume":"111","issue":"2","pages":"281","abstract":"","topics":["epistemology","mind"],"si":null,"url":"https://doi.org/10.2307/3182627"},{"doi":"10.1215/00318108-111-2-243","title":"The Formal-Structural View of Logical Consequence: A Reply to Gila Sher","authors":["William H. Hanson"],"journal":"phil-review","published":"2002-04-01","volume":"111","issue":"2","pages":"243-258","abstract":"","topics":["logic"],"si":null,"url":"https://doi.org/10.1215/00318108-111-2-243"},{"doi":"10.1215/00318108-111-2-323","title":"Foundations of Hegel's Social Theory: Actualizing Freedom","authors":["Terry Pinkard"],"journal":"phil-review","published":"2002-04-01","volume":"111","issue":"2","pages":"323-326","abstract":"","topics":["history"],"si":null,"url":"https://doi.org/10.1215/00318108-111-2-323"},{"doi":"10.1215/00318108-111-2-302","title":"Aristotle on Meaning and Essence","authors":["Travis Butler"],"journal":"phil-review","published":"2002-04-01","volume":"111","issue":"2","pages":"302-305","abstract":"","topics":["history","language","metaphysics"],"si":null,"url":"https://doi.org/10.1215/00318108-111-2-302"},{"doi":"10.2307/3182629","title":"Truth, Rationality, and Self-Control: Themes from Peirce","authors":["Douglas Anderson","Christopher Hookway"],"journal":"phil-review","published":"2002-04-01","volume":"111","issue":"2","pages":"288","abstract":"","topics":["epistemology"],"si":null,"url":"https://doi.org/10.2307/3182629"},{"doi":"10.1215/00318108-111-2-327","title":"Logic and Language in Wittgenstein's Tractatus","authors":["Michael Kremer"],"journal":"phil-review","published":"2002-04-01","volume":"111","issue":"2","pages":"327-330","abstract":"","topics":["history","language","logic"],"si":null,"url":"https://doi.org/10.1215/00318108-111-2-327"},{"doi":"10.2307/3182636","title":"Life's Form: Late Aristotelian Conceptions of the Soul","authors":["Robert Pasnau","Dennis Des Chene"],"journal":"phil-review","published":"2002-04-01","volume":"111","issue":"2","pages":"308","abstract":"","topics":["history","religion"],"si":null,"url":"https://doi.org/10.2307/3182636"},{"doi":"10.1215/00318108-111-2-291","title":"Causing Actions","authors":["Georg Theiner","Timothy O'Connor"],"journal":"phil-review","published":"2002-04-01","volume":"111","issue":"2","pages":"291-294","abstract":"","topics":[],"si":null,"url":"https://doi.org/10.1215/00318108-111-2-291"},{"doi":"10.2307/3182620","title":"Reply to Huemer on the Consequence Argument","authors":["Helen Beebee"],"journal":"phil-review","published":"2002-04-01","volume":"111","issue":"2","pages":"235","abstract":"","topics":[],"si":null,"url":"https://doi.org/10.2307/3182620"},{"doi":"10.2307/3182619","title":"What Could Antirealism about Ordinary Psychology Possibly Be?","authors":["Crispin Wright"],"journal":"phil-review","published":"2002-04-01","volume":"111","issue":"2","pages":"205","abstract":"","topics":["metaphysics"],"si":null,"url":"https://doi.org/10.2307/3182619"},{"doi":"10.2307/3182637","title":"On the Purity of the Art of Logic: The Shorter and the Longer Treatises","authors":["E. J. Ashworth","Walter Burley","Paul Vincent Spade"],"journal":"phil-review","published":"2002-04-01","volume":"111","issue":"2","pages":"311","abstract":"","topics":["aesthetics","logic"],"si":null,"url":"https://doi.org/10.2307/3182637"},{"doi":"10.2307/3182630","title":"Causing Actions","authors":["Georg Theiner","Timothy O'Connor","Paul M. Pietroski"],"journal":"phil-review","published":"2002-04-01","volume":"111","issue":"2","pages":"291","abstract":"","topics":[],"si":null,"url":"https://doi.org/10.2307/3182630"},{"doi":"10.1215/00318108-111-2-318","title":"The Cambridge Companion to German Idealism","authors":["Klaus Brinkmann"],"journal":"phil-review","published":"2002-04-01","volume":"111","issue":"2","pages":"318-323","abstract":"","topics":[],"si":null,"url":"https://doi.org/10.1215/00318108-111-2-318"},{"doi":"10.2307/3182634","title":"Aristotle on Meaning and Essence","authors":["Travis Butler","David Charles"],"journal":"phil-review","published":"2002-04-01","volume":"111","issue":"2","pages":"302","abstract":"","topics":["history","language","metaphysics"],"si":null,"url":"https://doi.org/10.2307/3182634"},{"doi":"10.1215/00318108-111-2-299","title":"Plato and His Predecessors: The Dramatisation of Reason","authors":["John Palmer"],"journal":"phil-review","published":"2002-04-01","volume":"111","issue":"2","pages":"299-302","abstract":"","topics":["history"],"si":null,"url":"https://doi.org/10.1215/00318108-111-2-299"},{"doi":"10.1215/00318108-111-2-305","title":"Reading Neoplatonism: Nondiscursive Thinking in the Texts of Plotinus, Proclus, and Damascius","authors":["Dominic J. O'Meara"],"journal":"phil-review","published":"2002-04-01","volume":"111","issue":"2","pages":"305-308","abstract":"","topics":[],"si":null,"url":"https://doi.org/10.1215/00318108-111-2-305"},{"doi":"10.2307/3182635","title":"Reading Neoplatonism: Nondiscursive Thinking in the Texts of Plotinus, Proclus, and Damascius","authors":["Dominic J. O'Meara","Sara Rappe"],"journal":"phil-review","published":"2002-04-01","volume":"111","issue":"2","pages":"305","abstract":"","topics":[],"si":null,"url":"https://doi.org/10.2307/3182635"},{"doi":"10.2307/3182640","title":"Foundations of Hegel's Social Theory: Actualizing Freedom","authors":["Terry Pinkard","Frederick Neuhouser"],"journal":"phil-review","published":"2002-04-01","volume":"111","issue":"2","pages":"323","abstract":"","topics":["history"],"si":null,"url":"https://doi.org/10.2307/3182640"},{"doi":"10.1215/00318108-111-2-278","title":"Semantics, Tense, and Time","authors":["Quentin Smith"],"journal":"phil-review","published":"2002-04-01","volume":"111","issue":"2","pages":"278-281","abstract":"","topics":["language","metaphysics"],"si":null,"url":"https://doi.org/10.1215/00318108-111-2-278"},{"doi":"10.1215/00318108-111-2-294","title":"Cause and Explanation in Ancient Greek Thought","authors":["Michael Ferejohn"],"journal":"phil-review","published":"2002-04-01","volume":"111","issue":"2","pages":"294-296","abstract":"","topics":["history","philsci"],"si":null,"url":"https://doi.org/10.1215/00318108-111-2-294"},{"doi":"10.1215/00318108-111-2-205","title":"What Could Antirealism about Ordinary Psychology Possibly Be?","authors":["Crispin Wright"],"journal":"phil-review","published":"2002-04-01","volume":"111","issue":"2","pages":"205-233","abstract":"","topics":["metaphysics"],"si":null,"url":"https://doi.org/10.1215/00318108-111-2-205"},{"doi":"10.1215/00318108-111-2-308","title":"Life's Form: Late Aristotelian Conceptions of the Soul","authors":["Robert Pasnau"],"journal":"phil-review","published":"2002-04-01","volume":"111","issue":"2","pages":"308-310","abstract":"","topics":["history","religion"],"si":null,"url":"https://doi.org/10.1215/00318108-111-2-308"},{"doi":"10.1215/00318108-111-2-288","title":"Truth, Rationality, and Self-Control: Themes from Peirce","authors":["Douglas Anderson"],"journal":"phil-review","published":"2002-04-01","volume":"111","issue":"2","pages":"288-291","abstract":"","topics":["epistemology"],"si":null,"url":"https://doi.org/10.1215/00318108-111-2-288"},{"doi":"10.2307/3182626","title":"Semantics, Tense, and Time","authors":["Quentin Smith","Peter Ludlow"],"journal":"phil-review","published":"2002-04-01","volume":"111","issue":"2","pages":"278","abstract":"","topics":["language","metaphysics"],"si":null,"url":"https://doi.org/10.2307/3182626"},{"doi":"10.1215/00318108-111-2-281","title":"Knowledge, Mind, and the Given: Reading Wilfrid Sellars's “Empiricism and the Philosophy of Mind”","authors":["Danielle Macbeth"],"journal":"phil-review","published":"2002-04-01","volume":"111","issue":"2","pages":"281-284","abstract":"","topics":["epistemology","mind"],"si":null,"url":"https://doi.org/10.1215/00318108-111-2-281"},{"doi":"10.1215/00318108-111-2-275","title":"Inalienable Rights: The Limits of Consent in Medicine and the Law","authors":["Scott Kim"],"journal":"phil-review","published":"2002-04-01","volume":"111","issue":"2","pages":"275-278","abstract":"","topics":["ethics","philsci","political"],"si":null,"url":"https://doi.org/10.1215/00318108-111-2-275"},{"doi":"10.2307/3182638","title":"Berkeley's Thought","authors":["Lex Newman","George S. Pappas"],"journal":"phil-review","published":"2002-04-01","volume":"111","issue":"2","pages":"314","abstract":"","topics":["history"],"si":null,"url":"https://doi.org/10.2307/3182638"},{"doi":"10.2307/3182625","title":"Inalienable Rights: The Limits of Consent in Medicine and the Law","authors":["Scott Kim","Terrance McConnell"],"journal":"phil-review","published":"2002-04-01","volume":"111","issue":"2","pages":"275","abstract":"","topics":["ethics","philsci","political"],"si":null,"url":"https://doi.org/10.2307/3182625"},{"doi":"10.2307/3182618","title":"Assertion, Knowledge, and Context","authors":["Keith DeRose"],"journal":"phil-review","published":"2002-04-01","volume":"111","issue":"2","pages":"167","abstract":"","topics":["epistemology","language"],"si":null,"url":"https://doi.org/10.2307/3182618"},{"doi":"10.2307/3182641","title":"Logic and Language in Wittgenstein's \"Tractatus\"","authors":["Michael Kremer","Ian Proops"],"journal":"phil-review","published":"2002-04-01","volume":"111","issue":"2","pages":"327","abstract":"","topics":["history","language","logic"],"si":null,"url":"https://doi.org/10.2307/3182641"},{"doi":"10.2307/3182632","title":"Platonic Questions: Dialogues with the Silent Philosopher","authors":["Chris Bobonich","Diskin Clay"],"journal":"phil-review","published":"2002-04-01","volume":"111","issue":"2","pages":"297","abstract":"","topics":["history"],"si":null,"url":"https://doi.org/10.2307/3182632"},{"doi":"10.1215/00318108-111-2-311","title":"On the Purity of the Art of Logic: The Shorter and the Longer Treatises","authors":["E. J. Ashworth"],"journal":"phil-review","published":"2002-04-01","volume":"111","issue":"2","pages":"311-313","abstract":"","topics":["aesthetics","logic"],"si":null,"url":"https://doi.org/10.1215/00318108-111-2-311"},{"doi":"10.2307/3182577","title":"Kant's Theory of Moral Motivation","authors":["David Sussman","Daniel Guevara"],"journal":"phil-review","published":"2002-01-01","volume":"111","issue":"1","pages":"116","abstract":"","topics":["ethics","history"],"si":null,"url":"https://doi.org/10.2307/3182577"},{"doi":"10.1215/00318108-111-1-142","title":"RELATIVISM AND REALITY: A CONTEMPORARY INTRODUCTION; SCIENTIFIC REALISM: HOW SCIENCE TRACKS TRUTH","authors":["Gerald Doppelt"],"journal":"phil-review","published":"2002-01-01","volume":"111","issue":"1","pages":"142-147","abstract":"","topics":["metaphysics","philsci"],"si":null,"url":"https://doi.org/10.1215/00318108-111-1-142"},{"doi":"10.2307/3182572","title":"Aristotle's Theory of Substance","authors":["Charlotte Witt","Michael Wedin"],"journal":"phil-review","published":"2002-01-01","volume":"111","issue":"1","pages":"98","abstract":"","topics":["history"],"si":null,"url":"https://doi.org/10.2307/3182572"},{"doi":"10.2307/3182578","title":"A Parting of the Ways: Carnap, Cassirer, and Heidegger","authors":["Michael Roubach","Michael Friedman"],"journal":"phil-review","published":"2002-01-01","volume":"111","issue":"1","pages":"119","abstract":"","topics":["history"],"si":null,"url":"https://doi.org/10.2307/3182578"},{"doi":"10.2307/3182587","title":"Illocutionary Acts and Sentence Meaning","authors":["Mandy Simons","William P. Alston"],"journal":"phil-review","published":"2002-01-01","volume":"111","issue":"1","pages":"152","abstract":"","topics":["language"],"si":null,"url":"https://doi.org/10.2307/3182587"},{"doi":"10.1215/00318108-111-1-116","title":"KANT'S THEORY OF MORAL MOTIVATION","authors":["David Sussman"],"journal":"phil-review","published":"2002-01-01","volume":"111","issue":"1","pages":"116-119","abstract":"","topics":["ethics","history"],"si":null,"url":"https://doi.org/10.1215/00318108-111-1-116"},{"doi":"10.2307/3182583","title":"A Theory of Sentience","authors":["Susanna Siegel","Austen Clark"],"journal":"phil-review","published":"2002-01-01","volume":"111","issue":"1","pages":"135","abstract":"","topics":[],"si":null,"url":"https://doi.org/10.2307/3182583"},{"doi":"10.2307/3182582","title":"The Emotions: A Philosophical Exploration","authors":["Bennett W. Helm","Peter Goldie"],"journal":"phil-review","published":"2002-01-01","volume":"111","issue":"1","pages":"132","abstract":"","topics":["mind"],"si":null,"url":"https://doi.org/10.2307/3182582"},{"doi":"10.1215/00318108-111-1-108","title":"THE CAMBRIDGE COMPANION TO MALEBRANCHE","authors":["Catherine Wilson"],"journal":"phil-review","published":"2002-01-01","volume":"111","issue":"1","pages":"108-113","abstract":"","topics":[],"si":null,"url":"https://doi.org/10.1215/00318108-111-1-108"},{"doi":"10.1215/00318108-111-1-113","title":"CRITIQUE OF PURE REASON","authors":["Günter Zöller"],"journal":"phil-review","published":"2002-01-01","volume":"111","issue":"1","pages":"113-116","abstract":"","topics":[],"si":null,"url":"https://doi.org/10.1215/00318108-111-1-113"},{"doi":"10.1215/00318108-111-1-122","title":"ON VIRTUE ETHICS","authors":["Julia Driver"],"journal":"phil-review","published":"2002-01-01","volume":"111","issue":"1","pages":"122-127","abstract":"","topics":["ethics"],"si":null,"url":"https://doi.org/10.1215/00318108-111-1-122"},{"doi":"10.2307/3182568","title":"Rational Choice and Action Omnipotence","authors":["John L. Pollock"],"journal":"phil-review","published":"2002-01-01","volume":"111","issue":"1","pages":"1","abstract":"","topics":["action"],"si":null,"url":"https://doi.org/10.2307/3182568"},{"doi":"10.2307/3182584","title":"Persons and Bodies: A Constitution View","authors":["Peter van Inwagen","Lynne Rudder Baker"],"journal":"phil-review","published":"2002-01-01","volume":"111","issue":"1","pages":"138","abstract":"","topics":[],"si":null,"url":"https://doi.org/10.2307/3182584"},{"doi":"10.1215/00318108-111-1-152","title":"ILLOCUTIONARY ACTS AND SENTENCE MEANING","authors":["Mandy Simons"],"journal":"phil-review","published":"2002-01-01","volume":"111","issue":"1","pages":"152-155","abstract":"","topics":["language"],"si":null,"url":"https://doi.org/10.1215/00318108-111-1-152"},{"doi":"10.1215/00318108-111-1-95","title":"PLATO AND THE HERO: COURAGE, MANLINESS AND THE IMPERSONAL GOOD","authors":["Raphael Woolf"],"journal":"phil-review","published":"2002-01-01","volume":"111","issue":"1","pages":"95-97","abstract":"","topics":["history"],"si":null,"url":"https://doi.org/10.1215/00318108-111-1-95"},{"doi":"10.1215/00318108-111-1-130","title":"FROM CHANCE TO CHOICE: GENETICS AND JUSTICE","authors":["Edward Stein"],"journal":"phil-review","published":"2002-01-01","volume":"111","issue":"1","pages":"130-132","abstract":"","topics":["political"],"si":null,"url":"https://doi.org/10.1215/00318108-111-1-130"},{"doi":"10.2307/3182574","title":"Insight and Inference: Descartes's Founding Principle and Modern Philosophy","authors":["Lawrence Nolan","Murray Miles"],"journal":"phil-review","published":"2002-01-01","volume":"111","issue":"1","pages":"105","abstract":"","topics":["history","logic"],"si":null,"url":"https://doi.org/10.2307/3182574"},{"doi":"10.2307/3182575","title":"The Cambridge Companion to Malebranche","authors":["Catherine Wilson","Steven Nadler"],"journal":"phil-review","published":"2002-01-01","volume":"111","issue":"1","pages":"108","abstract":"","topics":[],"si":null,"url":"https://doi.org/10.2307/3182575"},{"doi":"10.1215/00318108-111-1-119","title":"A PARTING OF THE WAYS: CARNAP, CASSIRER, AND HEIDEGGER","authors":["Michael Roubach"],"journal":"phil-review","published":"2002-01-01","volume":"111","issue":"1","pages":"119-122","abstract":"","topics":["history"],"si":null,"url":"https://doi.org/10.1215/00318108-111-1-119"},{"doi":"10.1215/00318108-111-1-98","title":"ARISTOTLE'S THEORY OF SUBSTANCE","authors":["Charlotte Witt"],"journal":"phil-review","published":"2002-01-01","volume":"111","issue":"1","pages":"98-101","abstract":"","topics":["history"],"si":null,"url":"https://doi.org/10.1215/00318108-111-1-98"},{"doi":"10.2307/3182570","title":"Evidence, Pragmatics, and Justification","authors":["Jeremy Fantl","Matthew McGrath"],"journal":"phil-review","published":"2002-01-01","volume":"111","issue":"1","pages":"67","abstract":"","topics":["epistemology","language"],"si":null,"url":"https://doi.org/10.2307/3182570"},{"doi":"10.2307/3182573","title":"The Cambridge History of Hellenistic Philosophy","authors":["R. W. Sharples","Keimpe Algra","Jonathan Barnes","Jaap Mansfeld","Malcolm Schofield"],"journal":"phil-review","published":"2002-01-01","volume":"111","issue":"1","pages":"101","abstract":"","topics":[],"si":null,"url":"https://doi.org/10.2307/3182573"},{"doi":"10.1215/00318108-111-1-25","title":"Frege, Kant, and the Logic in Logicism","authors":["John MacFarlane"],"journal":"phil-review","published":"2002-01-01","volume":"111","issue":"1","pages":"25-65","abstract":"","topics":["history","logic"],"si":null,"url":"https://doi.org/10.1215/00318108-111-1-25"},{"doi":"10.1215/00318108-111-1-135","title":"A THEORY OF SENTIENCE","authors":["Susanna Siegel"],"journal":"phil-review","published":"2002-01-01","volume":"111","issue":"1","pages":"135-138","abstract":"","topics":[],"si":null,"url":"https://doi.org/10.1215/00318108-111-1-135"},{"doi":"10.1215/00318108-111-1-148","title":"GÖDEL MEETS EINSTEIN: TIME TRAVEL IN THE GÖDEL UNIVERSE.","authors":["Steven Weinstein"],"journal":"phil-review","published":"2002-01-01","volume":"111","issue":"1","pages":"148-152","abstract":"","topics":["metaphysics"],"si":null,"url":"https://doi.org/10.1215/00318108-111-1-148"},{"doi":"10.1215/00318108-111-1-105","title":"INSIGHT AND INFERENCE: DESCARTES'S FOUNDING PRINCIPLE AND MODERN PHILOSOPHY","authors":["Lawrence Nolan"],"journal":"phil-review","published":"2002-01-01","volume":"111","issue":"1","pages":"105-108","abstract":"","topics":["history","logic"],"si":null,"url":"https://doi.org/10.1215/00318108-111-1-105"},{"doi":"10.1215/00318108-111-1-1","title":"Rational Choice and Action Omnipotence","authors":["John L. Pollock"],"journal":"phil-review","published":"2002-01-01","volume":"111","issue":"1","pages":"1-23","abstract":"","topics":["action"],"si":null,"url":"https://doi.org/10.1215/00318108-111-1-1"},{"doi":"10.2307/3182586","title":"Godel Meets Einstein: Time Travel in the Godel Universe","authors":["Steven Weinstein","Palle Yourgrau"],"journal":"phil-review","published":"2002-01-01","volume":"111","issue":"1","pages":"148","abstract":"","topics":["metaphysics"],"si":null,"url":"https://doi.org/10.2307/3182586"},{"doi":"10.2307/3182569","title":"Frege, Kant, and the Logic in Logicism","authors":["John MacFarlane"],"journal":"phil-review","published":"2002-01-01","volume":"111","issue":"1","pages":"25","abstract":"","topics":["history","logic"],"si":null,"url":"https://doi.org/10.2307/3182569"},{"doi":"10.1215/00318108-111-1-138","title":"PERSONS AND BODIES: A CONSTITUTION VIEW","authors":["Peter Van Inwagen"],"journal":"phil-review","published":"2002-01-01","volume":"111","issue":"1","pages":"138-141","abstract":"","topics":[],"si":null,"url":"https://doi.org/10.1215/00318108-111-1-138"},{"doi":"10.1215/00318108-111-1-101","title":"THE CAMBRIDGE HISTORY OF HELLENISTIC PHILOSOPHY","authors":["R. W. Sharples"],"journal":"phil-review","published":"2002-01-01","volume":"111","issue":"1","pages":"101-105","abstract":"","topics":[],"si":null,"url":"https://doi.org/10.1215/00318108-111-1-101"},{"doi":"10.2307/3182571","title":"Plato and the Hero: Courage, Manliness and the Impersonal Good","authors":["Raphael Woolf","Angela Hobbs"],"journal":"phil-review","published":"2002-01-01","volume":"111","issue":"1","pages":"95","abstract":"","topics":["history"],"si":null,"url":"https://doi.org/10.2307/3182571"},{"doi":"10.1215/00318108-111-1-127","title":"ETHICAL NORMS, PARTICULAR CASES","authors":["Don Loeb"],"journal":"phil-review","published":"2002-01-01","volume":"111","issue":"1","pages":"127-129","abstract":"","topics":["ethics"],"si":null,"url":"https://doi.org/10.1215/00318108-111-1-127"},{"doi":"10.2307/3182585","title":"Relativism and Reality: A Contemporary Introduction","authors":["Gerald Doppelt","Robert Kirk","Stathis Psillos"],"journal":"phil-review","published":"2002-01-01","volume":"111","issue":"1","pages":"142","abstract":"","topics":[],"si":null,"url":"https://doi.org/10.2307/3182585"},{"doi":"10.1215/00318108-111-1-67","title":"Evidence, Pragmatics, and Justification","authors":["Jeremy Fantl","Matthew McGrath"],"journal":"phil-review","published":"2002-01-01","volume":"111","issue":"1","pages":"67-94","abstract":"","topics":["epistemology","language"],"si":null,"url":"https://doi.org/10.1215/00318108-111-1-67"},{"doi":"10.2307/3182580","title":"Ethical Norms, Particular Cases","authors":["Don Loeb","James D. Wallace"],"journal":"phil-review","published":"2002-01-01","volume":"111","issue":"1","pages":"127","abstract":"","topics":["ethics"],"si":null,"url":"https://doi.org/10.2307/3182580"},{"doi":"10.2307/3182581","title":"From Chance to Choice: Genetics and Justice","authors":["Edward Stein","Allen Buchanan","Dan W. Brock","Norman Daniels","Daniel Wikler"],"journal":"phil-review","published":"2002-01-01","volume":"111","issue":"1","pages":"130","abstract":"","topics":["political"],"si":null,"url":"https://doi.org/10.2307/3182581"},{"doi":"10.1215/00318108-111-1-132","title":"THE EMOTIONS: A PHILOSOPHICAL EXPLORATION","authors":["Bennett W. Helm"],"journal":"phil-review","published":"2002-01-01","volume":"111","issue":"1","pages":"132-135","abstract":"","topics":["mind"],"si":null,"url":"https://doi.org/10.1215/00318108-111-1-132"},{"doi":"10.2307/3182579","title":"On Virtue Ethics","authors":["Julia Driver","Rosalind Hursthouse"],"journal":"phil-review","published":"2002-01-01","volume":"111","issue":"1","pages":"122","abstract":"","topics":["ethics"],"si":null,"url":"https://doi.org/10.2307/3182579"},{"doi":"10.2307/3182576","title":"Critique of Pure Reason","authors":["Gunter Zoller","Immanuel Kant","Paul Guyer","Allen W. Wood"],"journal":"phil-review","published":"2002-01-01","volume":"111","issue":"1","pages":"113","abstract":"","topics":[],"si":null,"url":"https://doi.org/10.2307/3182576"}]